chpi_long_decoder_rgb24_area_min.v
`timescale 1ns/1ps

module chpi_decode_20b_stream_top (
  input  wire        clk,
  input  wire        rst_n,
  input  wire        valid_i,
  input  wire [19:0] chpi_in,
  output wire        rgb_valid,
  output wire [23:0] rgb_data,
  output wire        useful20_valid,
  output wire [19:0] useful20_data
);
  chpi_420b413b_rgb24_stream_dec u_dec (
    .clk            (clk),
    .rst_n          (rst_n),
    .valid_i        (valid_i),
    .chpi_in        (chpi_in),
    .rgb_valid      (rgb_valid),
    .rgb_data       (rgb_data),
    .useful20_valid (useful20_valid),
    .useful20_data  (useful20_data)
  );
endmodule

module chpi_420b413b_rgb24_stream_dec (
  input  wire        clk,
  input  wire        rst_n,
  input  wire        valid_i,
  input  wire [19:0] chpi_in,
  output reg         rgb_valid,
  output reg  [23:0] rgb_data,
  output wire        useful20_valid,
  output wire [19:0] useful20_data
);
  // Production candidate Ver.O/min: area-first CHPI 420b-to-RGB24 decoder.
  // External input is only CHPI[19:0], LSB first, one 20b word per clock.
  // The upstream K-code/bit-slip aligner must release this block with the
  // first active clock aligned to packet bit0. This decoder does not search
  // K-code, does not do bit-slip, and does not support valid_i bubbles.
  // valid_i is kept only for top-level interface compatibility.
  //
  // One 420b packet is 21 clocks. The first 7b group is header {H, Label};
  // it updates label state and is not sent to RGB. The remaining 59 groups
  // are restored payload groups, then packed directly into RGB24.
  //
  // Area choices:
  // - 20b-to-7b uses fixed subphase case placement, not a generic FIFO.
  // - packet position is packet_phase[1:0] + subphase[2:0], not a 5b counter.
  // - 7b payload groups first become bytes, then byte lanes form RGB24.
  // - useful20 debug output is tied off so no extra debug FIFO is synthesized.

  assign useful20_valid = 1'b0;
  assign useful20_data  = 20'd0;

  reg [5:0] raw_residue;
  reg [2:0] subphase;
  reg [1:0] packet_phase;
  wire      header_word;

  reg [5:0] active_label;
  reg       restore_enable;

  reg [6:0]  byte_residue;
  reg [2:0]  byte_bit_count;
  reg [15:0] rgb_byte_buf;
  reg [1:0]  rgb_byte_count;

  reg [6:0] group0_bits;
  reg [6:0] group1_bits;
  reg [6:0] group2_bits;
  reg       group2_valid;
  reg [5:0] raw_residue_next;

  reg [5:0] header_label;
  reg       header_restore_enable;
  reg [5:0] payload_label;
  reg       payload_restore_enable;

  reg [6:0] payload0_bits;
  reg [6:0] payload1_bits;
  reg [6:0] payload2_bits;
  reg [20:0] payload_bits;
  reg [4:0]  payload_bit_count;

  reg [27:0] byte_full;
  reg [4:0]  bit_total_count;
  reg [1:0]  new_byte_count;
  reg [7:0]  new_byte0;
  reg [7:0]  new_byte1;
  reg [7:0]  new_byte2;
  reg [6:0]  byte_residue_next;
  reg [2:0]  byte_bit_count_next;

  reg [39:0] byte_pack_full;
  reg [2:0]  total_byte_count;
  reg [15:0] rgb_byte_buf_next;
  reg [1:0]  rgb_byte_count_next;
  reg        pack_emit_valid;
  reg [23:0] pack_emit_data;

  assign header_word = (packet_phase == 2'd0) && (subphase == 3'd0);

  function [6:0] restore_payload_group;
    input [6:0] group_bits;
    input [5:0] label_bits;
    input       label_is_active;
    begin
      if (label_is_active && (group_bits[6:1] == label_bits)) begin
        if (group_bits[0]) begin
          restore_payload_group = 7'b1111111;
        end else begin
          restore_payload_group = 7'b0000000;
        end
      end else begin
        restore_payload_group = group_bits;
      end
    end
  endfunction

  // Fixed 20b-to-7b phase. subphase advances 0..6 with each valid 20b word.
  always @* begin
    group0_bits      = 7'd0;
    group1_bits      = 7'd0;
    group2_bits      = 7'd0;
    group2_valid     = 1'b0;
    raw_residue_next = raw_residue;

    case (subphase)
      3'd0: begin
        group0_bits      = chpi_in[6:0];
        group1_bits      = chpi_in[13:7];
        group2_bits      = 7'd0;
        group2_valid     = 1'b0;
        raw_residue_next = chpi_in[19:14];
      end
      3'd1: begin
        group0_bits      = {chpi_in[0], raw_residue[5:0]};
        group1_bits      = chpi_in[7:1];
        group2_bits      = chpi_in[14:8];
        group2_valid     = 1'b1;
        raw_residue_next = {1'b0, chpi_in[19:15]};
      end
      3'd2: begin
        group0_bits      = {chpi_in[1:0], raw_residue[4:0]};
        group1_bits      = chpi_in[8:2];
        group2_bits      = chpi_in[15:9];
        group2_valid     = 1'b1;
        raw_residue_next = {2'b00, chpi_in[19:16]};
      end
      3'd3: begin
        group0_bits      = {chpi_in[2:0], raw_residue[3:0]};
        group1_bits      = chpi_in[9:3];
        group2_bits      = chpi_in[16:10];
        group2_valid     = 1'b1;
        raw_residue_next = {3'b000, chpi_in[19:17]};
      end
      3'd4: begin
        group0_bits      = {chpi_in[3:0], raw_residue[2:0]};
        group1_bits      = chpi_in[10:4];
        group2_bits      = chpi_in[17:11];
        group2_valid     = 1'b1;
        raw_residue_next = {4'b0000, chpi_in[19:18]};
      end
      3'd5: begin
        group0_bits      = {chpi_in[4:0], raw_residue[1:0]};
        group1_bits      = chpi_in[11:5];
        group2_bits      = chpi_in[18:12];
        group2_valid     = 1'b1;
        raw_residue_next = {5'b00000, chpi_in[19]};
      end
      3'd6: begin
        group0_bits      = {chpi_in[5:0], raw_residue[0]};
        group1_bits      = chpi_in[12:6];
        group2_bits      = chpi_in[19:13];
        group2_valid     = 1'b1;
        raw_residue_next = 6'd0;
      end
      default: begin
        group0_bits      = chpi_in[6:0];
        group1_bits      = chpi_in[13:7];
        group2_bits      = 7'd0;
        group2_valid     = 1'b0;
        raw_residue_next = chpi_in[19:14];
      end
    endcase
  end

  always @* begin
    header_label          = group0_bits[5:0];
    header_restore_enable = (group0_bits[5:0] != {6{~group0_bits[6]}});
    payload_label         = active_label;
    payload_restore_enable = restore_enable;

    if (header_word) begin
      payload_label          = header_label;
      payload_restore_enable = header_restore_enable;
    end
  end

  always @* begin
    payload0_bits     = 7'd0;
    payload1_bits     = 7'd0;
    payload2_bits     = 7'd0;
    payload_bits      = 21'd0;
    payload_bit_count = 5'd0;

    if (header_word) begin
      payload0_bits     = restore_payload_group(group1_bits,
                                                payload_label,
                                                payload_restore_enable);
      payload_bits[6:0] = payload0_bits;
      payload_bit_count = 5'd7;
    end else begin
      payload0_bits       = restore_payload_group(group0_bits,
                                                  payload_label,
                                                  payload_restore_enable);
      payload1_bits       = restore_payload_group(group1_bits,
                                                  payload_label,
                                                  payload_restore_enable);
      payload_bits[6:0]   = payload0_bits;
      payload_bits[13:7]  = payload1_bits;
      payload_bit_count   = 5'd14;

      if (group2_valid) begin
        payload2_bits       = restore_payload_group(group2_bits,
                                                    payload_label,
                                                    payload_restore_enable);
        payload_bits[20:14] = payload2_bits;
        payload_bit_count   = 5'd21;
      end
    end
  end

  // First pack 7b payload groups into bytes, then pack every three bytes into
  // one RGB24 word. This keeps the bit-level shifter local and only 28b wide.
  always @* begin
    byte_full            = {21'd0, byte_residue};
    bit_total_count      = {2'b00, byte_bit_count} + {1'b0, payload_bit_count};
    new_byte_count       = 2'd0;
    new_byte0            = 8'd0;
    new_byte1            = 8'd0;
    new_byte2            = 8'd0;
    byte_residue_next    = byte_residue;
    byte_bit_count_next  = byte_bit_count;

    byte_pack_full       = 40'd0;
    total_byte_count     = {1'b0, rgb_byte_count};
    rgb_byte_buf_next    = rgb_byte_buf;
    rgb_byte_count_next  = rgb_byte_count;
    pack_emit_valid      = 1'b0;
    pack_emit_data       = 24'd0;

    if (payload_bit_count != 5'd0) begin
      byte_full = byte_full | ({7'd0, payload_bits} << byte_bit_count);
      new_byte_count      = bit_total_count[4:3];
      new_byte0           = byte_full[7:0];
      new_byte1           = byte_full[15:8];
      new_byte2           = byte_full[23:16];
      byte_bit_count_next = bit_total_count[2:0];

      case (bit_total_count[4:3])
        2'd0: byte_residue_next = byte_full[6:0];
        2'd1: byte_residue_next = byte_full[14:8];
        2'd2: byte_residue_next = byte_full[22:16];
        default: byte_residue_next = {3'd0, byte_full[27:24]};
      endcase

      case (rgb_byte_count)
        2'd0: begin
          byte_pack_full[7:0]   = new_byte0;
          byte_pack_full[15:8]  = new_byte1;
          byte_pack_full[23:16] = new_byte2;
        end
        2'd1: begin
          byte_pack_full[7:0]   = rgb_byte_buf[7:0];
          byte_pack_full[15:8]  = new_byte0;
          byte_pack_full[23:16] = new_byte1;
          byte_pack_full[31:24] = new_byte2;
        end
        default: begin
          byte_pack_full[7:0]   = rgb_byte_buf[7:0];
          byte_pack_full[15:8]  = rgb_byte_buf[15:8];
          byte_pack_full[23:16] = new_byte0;
          byte_pack_full[31:24] = new_byte1;
          byte_pack_full[39:32] = new_byte2;
        end
      endcase

      total_byte_count = {1'b0, rgb_byte_count} + {1'b0, new_byte_count};

      if (total_byte_count >= 3'd3) begin
        pack_emit_valid = 1'b1;
        pack_emit_data  = byte_pack_full[23:0];
        case (total_byte_count - 3'd3)
          3'd0: begin
            rgb_byte_buf_next   = 16'd0;
            rgb_byte_count_next = 2'd0;
          end
          3'd1: begin
            rgb_byte_buf_next   = {8'd0, byte_pack_full[31:24]};
            rgb_byte_count_next = 2'd1;
          end
          default: begin
            rgb_byte_buf_next   = byte_pack_full[39:24];
            rgb_byte_count_next = 2'd2;
          end
        endcase
      end else begin
        rgb_byte_buf_next   = byte_pack_full[15:0];
        rgb_byte_count_next = total_byte_count[1:0];
      end
    end
  end

  always @(posedge clk or negedge rst_n) begin
    if (!rst_n) begin
      raw_residue <= 6'd0;
    end else begin
      raw_residue <= raw_residue_next;
    end
  end

  always @(posedge clk or negedge rst_n) begin
    if (!rst_n) begin
      subphase     <= 3'd0;
      packet_phase <= 2'd0;
    end else begin
      if (subphase == 3'd6) begin
        subphase <= 3'd0;
        if (packet_phase == 2'd2) begin
          packet_phase <= 2'd0;
        end else begin
          packet_phase <= packet_phase + 2'd1;
        end
      end else begin
        subphase <= subphase + 3'd1;
      end
    end
  end

  always @(posedge clk or negedge rst_n) begin
    if (!rst_n) begin
      active_label   <= 6'd0;
      restore_enable <= 1'b0;
    end else if (header_word) begin
      active_label   <= header_label;
      restore_enable <= header_restore_enable;
    end
  end

  always @(posedge clk or negedge rst_n) begin
    if (!rst_n) begin
      byte_residue   <= 7'd0;
      byte_bit_count <= 3'd0;
      rgb_byte_buf   <= 16'd0;
      rgb_byte_count <= 2'd0;
    end else begin
      byte_residue   <= byte_residue_next;
      byte_bit_count <= byte_bit_count_next;
      rgb_byte_buf   <= rgb_byte_buf_next;
      rgb_byte_count <= rgb_byte_count_next;
    end
  end

  always @(posedge clk or negedge rst_n) begin
    if (!rst_n) begin
      rgb_valid <= 1'b0;
      rgb_data  <= 24'd0;
    end else begin
      rgb_valid <= pack_emit_valid;
      if (pack_emit_valid) begin
        rgb_data <= pack_emit_data;
      end else begin
        rgb_data <= 24'd0;
      end
    end
  end
endmodule

chpi_long_decoder_rgb24_line_tb_aligned.v
`timescale 1ns/1ps

module chpi_long_decoder_rgb24_line_tb;
  localparam integer CTRL_BYTES   = 5;
  localparam integer RGB_BYTES    = 960;
  localparam integer LINE_BYTES   = CTRL_BYTES + RGB_BYTES;
  localparam integer LINE_BITS    = LINE_BYTES * 8;
  localparam integer BLOCKS       = (LINE_BITS + 412) / 413;
  localparam integer USEFUL_BITS  = BLOCKS * 413;
  localparam integer ENCODED_BITS = BLOCKS * 420;
  localparam integer RAW_WORDS    = ENCODED_BITS / 20;
  localparam integer OUT_RGB_WORDS = USEFUL_BITS / 24;
  localparam integer OUT_BYTES    = OUT_RGB_WORDS * 3;

  reg clk;
  reg rst_n;
  reg valid_i;
  reg [19:0] chpi_in;
  wire rgb_valid;
  wire [23:0] rgb_data;
  wire useful20_valid;
  wire [19:0] useful20_data;

  reg useful_bits [0:USEFUL_BITS-1];
  reg encoded_bits [0:ENCODED_BITS-1];
  reg used_label [0:63];

  integer i, j, blk, gi, bi, wi;
  integer enc_ptr;
  integer expected_byte_idx;
  integer mismatch_count;
  integer rgb_count;
  integer ctrl_ok_count;
  integer rgb_ok_count;
  integer done_count;
  reg [6:0] group;
  reg [6:0] enc_group;
  reg [6:0] header_group;
  reg [5:0] label;
  integer label_int;
  reg [7:0] value;
  reg [19:0] drive_word;

  chpi_decode_20b_stream_top dut (
    .clk            (clk),
    .rst_n          (rst_n),
    .valid_i        (valid_i),
    .chpi_in        (chpi_in),
    .rgb_valid      (rgb_valid),
    .rgb_data       (rgb_data),
    .useful20_valid (useful20_valid),
    .useful20_data  (useful20_data)
  );

  initial begin
    clk = 1'b0;
    forever #5 clk = ~clk; // 100 MHz
  end

  function [7:0] line_byte;
    input integer idx;
    begin
      case (idx)
        0: line_byte = 8'hc1;
        1: line_byte = 8'h7e;
        2: line_byte = 8'h55;
        3: line_byte = 8'haa;
        4: line_byte = 8'h5a;
        default: line_byte = (idx - CTRL_BYTES) & 8'hff;
      endcase
    end
  endfunction

  task append_group;
    input [6:0] g;
    integer n;
    begin
      for (n = 0; n < 7; n = n + 1) begin
        encoded_bits[enc_ptr] = g[n];
        enc_ptr = enc_ptr + 1;
      end
    end
  endtask

  task check_byte;
    input [7:0] got;
    reg [7:0] exp;
    begin
      if (expected_byte_idx < LINE_BYTES) begin
        exp = line_byte(expected_byte_idx);
        if (got !== exp) begin
          $display("ERROR line_byte[%0d] got=%02x exp=%02x time=%0t",
                   expected_byte_idx, got, exp, $time);
          mismatch_count = mismatch_count + 1;
        end else if (expected_byte_idx < CTRL_BYTES) begin
          ctrl_ok_count = ctrl_ok_count + 1;
          $display("CTRL PASS byte[%0d] = %02x time=%0t",
                   expected_byte_idx, got, $time);
        end else begin
          rgb_ok_count = rgb_ok_count + 1;
          if ((expected_byte_idx == CTRL_BYTES) ||
              (expected_byte_idx == CTRL_BYTES + RGB_BYTES - 1)) begin
            $display("RGB PASS byte[%0d] = %02x time=%0t",
                     expected_byte_idx - CTRL_BYTES, got, $time);
          end
        end
      end else if (got !== 8'h00) begin
        $display("ERROR padding_byte[%0d] got=%02x exp=00 time=%0t",
                 expected_byte_idx - LINE_BYTES, got, $time);
        mismatch_count = mismatch_count + 1;
      end
      expected_byte_idx = expected_byte_idx + 1;
    end
  endtask

  always @(posedge clk) begin
    if (!rst_n) begin
      expected_byte_idx <= 0;
      mismatch_count    <= 0;
      rgb_count         <= 0;
      ctrl_ok_count     <= 0;
      rgb_ok_count      <= 0;
      done_count        <= 0;
    end else if (rgb_valid) begin
      if (!done_count) begin
        rgb_count <= rgb_count + 1;
        check_byte(rgb_data[7:0]);
        if (expected_byte_idx >= LINE_BYTES) begin
          done_count <= 1;
        end else begin
          check_byte(rgb_data[15:8]);
          if (expected_byte_idx >= LINE_BYTES) begin
            done_count <= 1;
          end else begin
            check_byte(rgb_data[23:16]);
            if (expected_byte_idx >= LINE_BYTES) begin
              done_count <= 1;
            end
          end
        end
      end
    end
  end

  initial begin
    $dumpfile("chpi_long_decoder_rgb24_line_tb.vcd");
    $dumpvars(0, chpi_long_decoder_rgb24_line_tb);

    for (i = 0; i < USEFUL_BITS; i = i + 1) useful_bits[i] = 1'b0;
    for (i = 0; i < ENCODED_BITS; i = i + 1) encoded_bits[i] = 1'b0;

    for (i = 0; i < LINE_BYTES; i = i + 1) begin
      value = line_byte(i);
      for (j = 0; j < 8; j = j + 1) begin
        useful_bits[i*8 + j] = value[j];
      end
    end

    enc_ptr = 0;
    for (blk = 0; blk < BLOCKS; blk = blk + 1) begin
      for (i = 0; i < 64; i = i + 1) used_label[i] = 1'b0;

      for (gi = 0; gi < 59; gi = gi + 1) begin
        group = 7'd0;
        for (bi = 0; bi < 7; bi = bi + 1) begin
          group[bi] = useful_bits[blk*413 + gi*7 + bi];
        end
        if ((group != 7'b0000000) && (group != 7'b1111111)) begin
          used_label[group[6:1]] = 1'b1;
        end
      end

      label_int = 1;
      while ((label_int < 63) && used_label[label_int]) label_int = label_int + 1;
      label = label_int[5:0];
      header_group = {1'b1, label};
      append_group(header_group);

      for (gi = 0; gi < 59; gi = gi + 1) begin
        group = 7'd0;
        for (bi = 0; bi < 7; bi = bi + 1) begin
          group[bi] = useful_bits[blk*413 + gi*7 + bi];
        end

        if (group == 7'b0000000) enc_group = {label, 1'b0};
        else if (group == 7'b1111111) enc_group = {label, 1'b1};
        else enc_group = group;
        append_group(enc_group);
      end
    end

    $display("One-line test: CTRL_L=%0d bytes, RGB=%0d bytes, total=%0d bytes",
             CTRL_BYTES, RGB_BYTES, LINE_BYTES);
    $display("Line bits=%0d, CHPI blocks=%0d, encoded bits=%0d, raw 20b clocks=%0d",
             LINE_BITS, BLOCKS, ENCODED_BITS, RAW_WORDS);
    $display("Decoder can emit %0d RGB24 words = %0d bytes; padding bytes checked as zero",
             OUT_RGB_WORDS, OUT_BYTES);

    rst_n = 1'b0;
    valid_i = 1'b0;
    chpi_in = 20'd0;
    repeat (5) @(negedge clk);

    drive_word = 20'd0;
    for (bi = 0; bi < 20; bi = bi + 1) begin
      drive_word[bi] = encoded_bits[bi];
    end
    chpi_in = drive_word;
    valid_i = 1'b1;
    rst_n = 1'b1;

    for (wi = 1; wi < RAW_WORDS; wi = wi + 1) begin
      drive_word = 20'd0;
      for (bi = 0; bi < 20; bi = bi + 1) begin
        drive_word[bi] = encoded_bits[wi*20 + bi];
      end
      @(negedge clk);
      valid_i = 1'b1;
      chpi_in = drive_word;
    end

    @(negedge clk);
    valid_i = 1'b0;
    chpi_in = 20'd0;

    wait (done_count == 1);
    repeat (4) @(posedge clk);

    if ((mismatch_count == 0) &&
        (ctrl_ok_count == CTRL_BYTES) &&
        (rgb_ok_count == RGB_BYTES) &&
        (expected_byte_idx >= LINE_BYTES)) begin
      $display("PASS: complete line matched: %0d CTRL_L bytes + %0d RGB bytes",
               ctrl_ok_count, rgb_ok_count);
      $display("Output RGB24 words=%0d, checked bytes=%0d", rgb_count, expected_byte_idx);
    end else begin
      $display("FAIL: mismatches=%0d ctrl_ok=%0d/%0d rgb_ok=%0d/%0d checked=%0d",
               mismatch_count, ctrl_ok_count, CTRL_BYTES,
               rgb_ok_count, RGB_BYTES, expected_byte_idx);
    end
    $finish;
  end
endmodule

chpi_long_decoder_rgb24_line_tb.vcd
$date
	Mon Jun 08 02:38:02 2026
$end
$version
	Icarus Verilog
$end
$timescale
	1ps
$end
$scope module chpi_long_decoder_rgb24_line_tb $end
$var wire 20 ! useful20_data [19:0] $end
$var wire 1 " useful20_valid $end
$var wire 1 # rgb_valid $end
$var wire 24 $ rgb_data [23:0] $end
$var parameter 32 % BLOCKS $end
$var parameter 32 & CTRL_BYTES $end
$var parameter 32 ' ENCODED_BITS $end
$var parameter 32 ( LINE_BITS $end
$var parameter 32 ) LINE_BYTES $end
$var parameter 32 * OUT_BYTES $end
$var parameter 32 + OUT_RGB_WORDS $end
$var parameter 32 , RAW_WORDS $end
$var parameter 32 - RGB_BYTES $end
$var parameter 32 . USEFUL_BITS $end
$var reg 20 / chpi_in [19:0] $end
$var reg 1 0 clk $end
$var reg 20 1 drive_word [19:0] $end
$var reg 7 2 enc_group [6:0] $end
$var reg 7 3 group [6:0] $end
$var reg 7 4 header_group [6:0] $end
$var reg 6 5 label [5:0] $end
$var reg 1 6 rst_n $end
$var reg 1 7 valid_i $end
$var reg 8 8 value [7:0] $end
$var integer 32 9 bi [31:0] $end
$var integer 32 : blk [31:0] $end
$var integer 32 ; ctrl_ok_count [31:0] $end
$var integer 32 < done_count [31:0] $end
$var integer 32 = enc_ptr [31:0] $end
$var integer 32 > expected_byte_idx [31:0] $end
$var integer 32 ? gi [31:0] $end
$var integer 32 @ i [31:0] $end
$var integer 32 A j [31:0] $end
$var integer 32 B label_int [31:0] $end
$var integer 32 C mismatch_count [31:0] $end
$var integer 32 D rgb_count [31:0] $end
$var integer 32 E rgb_ok_count [31:0] $end
$var integer 32 F wi [31:0] $end
$scope function line_byte $end
$var integer 32 G idx [31:0] $end
$upscope $end
$scope module dut $end
$var wire 20 H chpi_in [19:0] $end
$var wire 1 0 clk $end
$var wire 1 6 rst_n $end
$var wire 20 I useful20_data [19:0] $end
$var wire 1 " useful20_valid $end
$var wire 1 7 valid_i $end
$var wire 1 # rgb_valid $end
$var wire 24 J rgb_data [23:0] $end
$scope module u_dec $end
$var wire 20 K chpi_in [19:0] $end
$var wire 1 0 clk $end
$var wire 1 L header_word $end
$var wire 1 6 rst_n $end
$var wire 20 M useful20_data [19:0] $end
$var wire 1 " useful20_valid $end
$var wire 1 7 valid_i $end
$var reg 6 N active_label [5:0] $end
$var reg 5 O bit_total_count [4:0] $end
$var reg 3 P byte_bit_count [2:0] $end
$var reg 3 Q byte_bit_count_next [2:0] $end
$var reg 28 R byte_full [27:0] $end
$var reg 40 S byte_pack_full [39:0] $end
$var reg 7 T byte_residue [6:0] $end
$var reg 7 U byte_residue_next [6:0] $end
$var reg 7 V group0_bits [6:0] $end
$var reg 7 W group1_bits [6:0] $end
$var reg 7 X group2_bits [6:0] $end
$var reg 1 Y group2_valid $end
$var reg 6 Z header_label [5:0] $end
$var reg 1 [ header_restore_enable $end
$var reg 8 \ new_byte0 [7:0] $end
$var reg 8 ] new_byte1 [7:0] $end
$var reg 8 ^ new_byte2 [7:0] $end
$var reg 2 _ new_byte_count [1:0] $end
$var reg 24 ` pack_emit_data [23:0] $end
$var reg 1 a pack_emit_valid $end
$var reg 2 b packet_phase [1:0] $end
$var reg 7 c payload0_bits [6:0] $end
$var reg 7 d payload1_bits [6:0] $end
$var reg 7 e payload2_bits [6:0] $end
$var reg 5 f payload_bit_count [4:0] $end
$var reg 21 g payload_bits [20:0] $end
$var reg 6 h payload_label [5:0] $end
$var reg 1 i payload_restore_enable $end
$var reg 6 j raw_residue [5:0] $end
$var reg 6 k raw_residue_next [5:0] $end
$var reg 1 l restore_enable $end
$var reg 16 m rgb_byte_buf [15:0] $end
$var reg 16 n rgb_byte_buf_next [15:0] $end
$var reg 2 o rgb_byte_count [1:0] $end
$var reg 2 p rgb_byte_count_next [1:0] $end
$var reg 24 q rgb_data [23:0] $end
$var reg 1 # rgb_valid $end
$var reg 3 r subphase [2:0] $end
$var reg 3 s total_byte_count [2:0] $end
$scope function restore_payload_group $end
$var reg 7 t group_bits [6:0] $end
$var reg 6 u label_bits [5:0] $end
$var reg 1 v label_is_active $end
$upscope $end
$upscope $end
$upscope $end
$scope task append_group $end
$var reg 7 w g [6:0] $end
$var integer 32 x n [31:0] $end
$upscope $end
$scope task check_byte $end
$var reg 8 y exp [7:0] $end
$var reg 8 z got [7:0] $end
$upscope $end
$upscope $end
$enddefinitions $end
$comment Show the parameter values. $end
$dumpall
b1111010100111 .
b1111000000 -
b110001111 ,
b101000110 +
b1111010010 *
b1111000101 )
b1111000101000 (
b1111100101100 '
b101 &
b10011 %
$end
#0
$dumpvars
bx z
bx y
b111 x
b100 w
1v
b0 u
b0 t
b0 s
b0 r
b0 q
b0 p
b0 o
b0 n
b0 m
0l
b0 k
b0 j
1i
b0 h
b0 g
b111 f
b0 e
b0 d
b0 c
b0 b
0a
b0 `
b0 _
b0 ^
b0 ]
b0 \
1[
b0 Z
0Y
b0 X
b0 W
b0 V
b0 U
b0 T
b0 S
b0 R
b111 Q
b0 P
b111 O
b0 N
b0 M
1L
b0 K
b0 J
b0 I
b0 H
b1111000100 G
bx F
bx E
bx D
bx C
b10 B
b1000 A
b1000000 @
b111011 ?
bx >
b1111100101100 =
bx <
bx ;
b10011 :
b111 9
b10111111 8
07
06
b10 5
b1000010 4
b0 3
b100 2
bx 1
00
b0 /
b0 $
0#
0"
b0 !
$end
#5000
b0 <
b0 E
b0 ;
b0 D
b0 C
b0 >
10
#10000
00
#15000
10
#20000
00
#25000
10
#30000
00
#35000
10
#40000
00
#45000
10
#50000
b1000001 n
b1000001 S
b1000001 U
b1000001 \
b1000001 R
b111 Q
b1000001 g
b1000001 c
b1000001 t
b110 u
b111 f
b110 h
1i
b110 Z
b111101 k
b1000001 W
b1000110 V
b1 F
16
17
b11110110000011000110 /
b11110110000011000110 H
b11110110000011000110 K
b10100 9
b1010101001010101011 1
00
#55000
b110001101111011000001 `
1a
b11000 ^
b1100000 e
b1100011 d
b1100000 t
b10101 f
b110000011000110111101 g
b111101 c
b111101 Z
b11110 k
1Y
b1100000 X
b1100011 W
b111101 V
0L
b0 p
b0 n
b11 s
b1100 U
b100 Q
b11011110 ]
b11 _
b1100000110001101111011000001 R
b110001101111011000001 S
b11000001 \
b11100 O
b111101 j
b1 r
1l
b110 N
b1000001 m
b111 P
b1000001 T
10
#60000
b10101010111111011000001 `
1a
b0 n
b11 s
b10101010111111011000001 S
b100 Q
b1010 U
b1010101 ^
b1111110 ]
b11000001 \
b11 _
b1010010101010111111011000001 R
b1010010 t
b10101 f
b101001010101011111101 g
b1010010 e
b1010101 d
b1111101 c
b1010 k
1Y
b1010010 X
b1010101 W
b1111101 V
b10100 9
b11001000000000101101 1
b10 F
b1010101001010101011 /
b1010101001010101011 H
b1010101001010101011 K
00
#65000
b101001 t
b10101 f
b10100101010101101010 g
b101001 e
b101010 d
b1101010 c
b101010 Z
b0 U
b1 Q
b101001010101011010101010 `
1a
b11 s
b101001010101011010101010 S
b10100101 ^
b1010110 ]
b10101010 \
b11 _
b11001 O
b101001010101011010101010 R
b101 k
1Y
b101001 X
b101010 W
b1101010 V
b10101010111111011000001 $
b10101010111111011000001 J
b10101010111111011000001 q
1#
b0 m
b100 P
b1010 T
b10 r
b1010 j
10
#70000
b101101010101010 `
1a
b11 s
b101101010101010 S
b1 Q
b1 U
b0 ^
b1011010 ]
b10101010 \
b11 _
b1000000000101101010101010 R
b1000000 t
b10101 f
b100000000010110101010 g
b1000000 e
b1011 d
b101010 c
b1100 k
1Y
b1000000 X
b1011 W
b101010 V
b10100 9
b1100000010000 1
b11 F
b11001000000000101101 /
b11001000000000101101 H
b11001000000000101101 K
00
#75000
b100000 t
b10101 f
b10000000001011011100 g
b100000 e
b101 d
b1011100 c
b11100 Z
b110 k
1Y
b100000 X
b101 W
b1011100 V
b10 p
b10110111001 n
b10000 U
b110 Q
b10000 ^
b0 `
0a
b10 s
b100000000010110111001 S
b101 ]
b10111001 \
b10 _
b10110 O
b100000000010110111001 R
b1100 j
b11 r
b1 P
b1 T
b101101010101010 $
b101101010101010 J
b101101010101010 q
b1 D
b11 >
b11 ;
b1010101 y
b10 G
b1010101 z
10
#80000
b10 p
b1000000001 n
b10 s
b110000001000000001 S
b110 Q
b11 U
b11 ^
b10 ]
b1 \
b10 _
b110000001000000001 R
b110 t
b10101 f
b11000000100000000 g
b110 e
b10 d
b0 c
b1100 Z
b0 k
1Y
b110 X
b10 W
b1100 V
b10100 9
b110000001010000010 1
b100 F
b1100000010000 /
b1100000010000 H
b1100000010000 K
00
#85000
b11 t
b10101 f
b1100000010000000 g
b11 e
b1 d
b0 Z
b11000000100000 n
b110000001000000001 `
1a
b101 s
b0 U
b11 Q
b11000000100000000000110000001000000001 S
b110000 ^
b100000 ]
b11 \
b11 _
b11011 O
b1100000010000000000011 R
1Y
b11 X
b1 W
b0 V
b0 $
b0 J
b0 q
0#
b10 o
b1000000001 m
b110 P
b11 T
b100 r
b0 j
b10 D
b1 E
b110 >
b101 ;
b0 y
b101 G
b0 z
10
#90000
b110000001000000001 `
1a
b10100000100 n
b101 s
b10100000100000000110000001000000001 S
b11 Q
b110 U
b101 ^
b100 ]
b11 \
b11 _
b110000001010000010000000011 R
b10000 Z
b10000 c
b1100000 t
b10101 f
b110000001010000010000 g
b1100000 e
b101000 d
b10000 V
1Y
b1100000 X
b101000 W
b10100 9
b10000100000000111000 1
b101 F
b110000001010000010 /
b110000001010000010 H
b110000001010000010 K
00
#95000
b110000 t
b10101 f
b11000000101000001000 g
b110000 e
b10100 d
b1000 c
b1000 Z
1Y
b110000 X
b10100 W
b1000 V
b110000001010000 n
b0 U
b0 Q
b10001100000010100000100 `
1a
b101 s
b110000001010000010001100000010100000100 S
b1100000 ^
b1010000 ]
b1000110 \
b11 _
b11000 O
b11000000101000001000110 R
b101 r
b10100000100 m
b11 P
b110 T
b110000001000000001 $
b110000001000000001 J
b110000001000000001 q
1#
10
#100000
b1100000010100000100 `
1a
b100000000111 n
b101 s
b100000000111000001100000010100000100 S
b0 Q
b0 U
b1000 ^
b111 ]
b110 \
b11 _
b10000000011100000110 R
b100 t
b10101 f
b10000000011100000 g
b100 e
b1 d
b1100000 c
b100000 Z
b1 k
1Y
b100 X
b1 W
b1100000 V
b10100 9
b1011000010100000100 1
b110 F
b10000100000000111000 /
b10000100000000111000 H
b10000100000000111000 K
00
#105000
b1000010 t
b10101 f
b100001000000001110001 g
b1000010 e
b0 d
b1110001 c
b110001 Z
b1 p
b10000000 n
b10000 U
b101 Q
b11100010000100000000111 `
1a
b100 s
b1000010000000011100010000100000000111 S
b10000 ^
b10000000 ]
b1110001 \
b10 _
b10101 O
b100001000000001110001 R
b0 k
1Y
b1000010 X
b0 W
b1110001 V
b1100000010100000100 $
b1100000010100000100 J
b1100000010100000100 q
b100000000111 m
b0 P
b0 T
b110 r
b1 j
b11 D
b1001 >
b100 E
b11 y
b1000 G
b11 z
10
#110000
b10010000100000000111 `
1a
b1 p
b1010 n
b100 s
b101100001010000010010000100000000111 S
b101 Q
b1011 U
b1011 ^
b1010 ]
b1001 \
b10 _
b10110000101000001001 R
b10100 d
b101100 t
b10101 f
b10110000101000001001 g
b101100 e
b1001 c
b1001 Z
b10100 W
b0 k
1Y
b101100 X
b1001 V
b10100 9
b110100001100000 1
b111 F
b1011000010100000100 /
b1011000010100000100 H
b1011000010100000100 K
00
