chpi_long_decoder_rgb24.v
`timescale 1ns/1ps

module chpi_decode_20b_stream_top (
  input  wire        clk,
  input  wire        rst_n,
  input  wire        valid_i,
  input  wire [19:0] chpi_in,
  output wire        rgb_valid,
  output wire [23:0] rgb_data,
  output wire        useful20_valid,
  output wire [19:0] useful20_data
);
  chpi_420b413b_rgb24_stream_dec u_dec (
    .clk            (clk),
    .rst_n          (rst_n),
    .valid_i        (valid_i),
    .chpi_in        (chpi_in),
    .rgb_valid      (rgb_valid),
    .rgb_data       (rgb_data),
    .useful20_valid (useful20_valid),
    .useful20_data  (useful20_data)
  );
endmodule

module chpi_420b413b_rgb24_stream_dec (
  input  wire        clk,
  input  wire        rst_n,
  input  wire        valid_i,
  input  wire [19:0] chpi_in,
  output reg         rgb_valid,
  output reg  [23:0] rgb_data,
  output reg         useful20_valid,
  output reg  [19:0] useful20_data
);
  reg [25:0] raw_fifo, raw_fifo_next;
  reg [5:0]  raw_cnt, raw_cnt_next;
  reg [31:0] rgb_fifo, rgb_fifo_next;
  reg [5:0]  rgb_cnt, rgb_cnt_next;
  reg [25:0] useful_fifo, useful_fifo_next;
  reg [5:0]  useful_cnt, useful_cnt_next;
  reg [8:0]  bit_cnt_420, bit_cnt_420_next;
  reg [5:0]  label_reg;
  reg        replace_en;
  reg        rgb_emit_done;
  reg        useful_emit_done;
  reg [6:0]  group_in, group_out;
  integer k;

  always @(posedge clk or negedge rst_n) begin
    if (!rst_n) begin
      rgb_valid      <= 1'b0;
      rgb_data       <= 24'd0;
      useful20_valid <= 1'b0;
      useful20_data  <= 20'd0;
      raw_fifo       <= 26'd0;
      raw_cnt        <= 6'd0;
      rgb_fifo       <= 32'd0;
      rgb_cnt        <= 6'd0;
      useful_fifo    <= 26'd0;
      useful_cnt     <= 6'd0;
      bit_cnt_420    <= 9'd0;
      label_reg      <= 6'd0;
      replace_en     <= 1'b0;
    end else begin
      rgb_valid      <= 1'b0;
      useful20_valid <= 1'b0;

      raw_fifo_next     = raw_fifo;
      raw_cnt_next      = raw_cnt;
      rgb_fifo_next     = rgb_fifo;
      rgb_cnt_next      = rgb_cnt;
      useful_fifo_next  = useful_fifo;
      useful_cnt_next   = useful_cnt;
      bit_cnt_420_next  = bit_cnt_420;
      rgb_emit_done     = 1'b0;
      useful_emit_done  = 1'b0;

      if (rgb_cnt_next >= 6'd24) begin
        rgb_data       <= rgb_fifo_next[23:0];
        rgb_valid      <= 1'b1;
        rgb_fifo_next  = rgb_fifo_next >> 24;
        rgb_cnt_next   = rgb_cnt_next - 6'd24;
        rgb_emit_done  = 1'b1;
      end

      if (useful_cnt_next >= 6'd20) begin
        useful20_data      <= useful_fifo_next[19:0];
        useful20_valid     <= 1'b1;
        useful_fifo_next   = useful_fifo_next >> 20;
        useful_cnt_next    = useful_cnt_next - 6'd20;
        useful_emit_done   = 1'b1;
      end

      if (valid_i) begin
        raw_fifo_next = raw_fifo_next | ({{6{1'b0}}, chpi_in} << raw_cnt_next);
        raw_cnt_next  = raw_cnt_next + 6'd20;
      end

      for (k = 0; k < 3; k = k + 1) begin
        if (raw_cnt_next >= 6'd7) begin
          group_in = raw_fifo_next[6:0];

          if (bit_cnt_420_next == 9'd0) begin
            label_reg  = group_in[5:0];
            replace_en = (group_in[5:0] != {6{~group_in[6]}});
          end else begin
            if (replace_en && (group_in[6:1] == label_reg)) begin
              group_out = group_in[0] ? 7'b1111111 : 7'b0000000;
            end else begin
              group_out = group_in;
            end

            rgb_fifo_next = rgb_fifo_next | ({{25{1'b0}}, group_out} << rgb_cnt_next);
            rgb_cnt_next  = rgb_cnt_next + 6'd7;

            useful_fifo_next = useful_fifo_next | ({{19{1'b0}}, group_out} << useful_cnt_next);
            useful_cnt_next  = useful_cnt_next + 6'd7;

            if (!rgb_emit_done && (rgb_cnt_next >= 6'd24)) begin
              rgb_data       <= rgb_fifo_next[23:0];
              rgb_valid      <= 1'b1;
              rgb_fifo_next  = rgb_fifo_next >> 24;
              rgb_cnt_next   = rgb_cnt_next - 6'd24;
              rgb_emit_done  = 1'b1;
            end

            if (!useful_emit_done && (useful_cnt_next >= 6'd20)) begin
              useful20_data      <= useful_fifo_next[19:0];
              useful20_valid     <= 1'b1;
              useful_fifo_next   = useful_fifo_next >> 20;
              useful_cnt_next    = useful_cnt_next - 6'd20;
              useful_emit_done   = 1'b1;
            end
          end

          raw_fifo_next    = raw_fifo_next >> 7;
          raw_cnt_next     = raw_cnt_next - 6'd7;
          bit_cnt_420_next = (bit_cnt_420_next == 9'd413) ? 9'd0
                                                          : bit_cnt_420_next + 9'd7;
        end
      end

      raw_fifo    <= raw_fifo_next;
      raw_cnt     <= raw_cnt_next;
      rgb_fifo    <= rgb_fifo_next;
      rgb_cnt     <= rgb_cnt_next;
      useful_fifo <= useful_fifo_next;
      useful_cnt  <= useful_cnt_next;
      bit_cnt_420 <= bit_cnt_420_next;
    end
  end
endmodule

chpi_long_decoder_rgb24_line_tb.v
`timescale 1ns/1ps

module chpi_long_decoder_rgb24_line_tb;
  localparam integer CTRL_BYTES   = 5;
  localparam integer RGB_BYTES    = 960;
  localparam integer LINE_BYTES   = CTRL_BYTES + RGB_BYTES;
  localparam integer LINE_BITS    = LINE_BYTES * 8;
  localparam integer BLOCKS       = (LINE_BITS + 412) / 413;
  localparam integer USEFUL_BITS  = BLOCKS * 413;
  localparam integer ENCODED_BITS = BLOCKS * 420;
  localparam integer RAW_WORDS    = ENCODED_BITS / 20;
  localparam integer OUT_RGB_WORDS = USEFUL_BITS / 24;
  localparam integer OUT_BYTES    = OUT_RGB_WORDS * 3;

  reg clk;
  reg rst_n;
  reg valid_i;
  reg [19:0] chpi_in;
  wire rgb_valid;
  wire [23:0] rgb_data;
  wire useful20_valid;
  wire [19:0] useful20_data;

  reg useful_bits [0:USEFUL_BITS-1];
  reg encoded_bits [0:ENCODED_BITS-1];
  reg used_label [0:63];

  integer i, j, blk, gi, bi, wi;
  integer enc_ptr;
  integer expected_byte_idx;
  integer mismatch_count;
  integer rgb_count;
  integer ctrl_ok_count;
  integer rgb_ok_count;
  reg [6:0] group;
  reg [6:0] enc_group;
  reg [6:0] header_group;
  reg [5:0] label;
  integer label_int;
  reg [7:0] value;
  reg [19:0] drive_word;

  chpi_decode_20b_stream_top dut (
    .clk            (clk),
    .rst_n          (rst_n),
    .valid_i        (valid_i),
    .chpi_in        (chpi_in),
    .rgb_valid      (rgb_valid),
    .rgb_data       (rgb_data),
    .useful20_valid (useful20_valid),
    .useful20_data  (useful20_data)
  );

  initial begin
    clk = 1'b0;
    forever #5 clk = ~clk; // 100 MHz
  end

  function [7:0] line_byte;
    input integer idx;
    begin
      case (idx)
        0: line_byte = 8'hc1;
        1: line_byte = 8'h7e;
        2: line_byte = 8'h55;
        3: line_byte = 8'haa;
        4: line_byte = 8'h5a;
        default: line_byte = (idx - CTRL_BYTES) & 8'hff;
      endcase
    end
  endfunction

  task append_group;
    input [6:0] g;
    integer n;
    begin
      for (n = 0; n < 7; n = n + 1) begin
        encoded_bits[enc_ptr] = g[n];
        enc_ptr = enc_ptr + 1;
      end
    end
  endtask

  task check_byte;
    input [7:0] got;
    reg [7:0] exp;
    begin
      if (expected_byte_idx < LINE_BYTES) begin
        exp = line_byte(expected_byte_idx);
        if (got !== exp) begin
          $display("ERROR line_byte[%0d] got=%02x exp=%02x time=%0t",
                   expected_byte_idx, got, exp, $time);
          mismatch_count = mismatch_count + 1;
        end else if (expected_byte_idx < CTRL_BYTES) begin
          ctrl_ok_count = ctrl_ok_count + 1;
          $display("CTRL PASS byte[%0d] = %02x time=%0t",
                   expected_byte_idx, got, $time);
        end else begin
          rgb_ok_count = rgb_ok_count + 1;
          if ((expected_byte_idx == CTRL_BYTES) ||
              (expected_byte_idx == CTRL_BYTES + RGB_BYTES - 1)) begin
            $display("RGB PASS byte[%0d] = %02x time=%0t",
                     expected_byte_idx - CTRL_BYTES, got, $time);
          end
        end
      end else if (got !== 8'h00) begin
        $display("ERROR padding_byte[%0d] got=%02x exp=00 time=%0t",
                 expected_byte_idx - LINE_BYTES, got, $time);
        mismatch_count = mismatch_count + 1;
      end
      expected_byte_idx = expected_byte_idx + 1;
    end
  endtask

  always @(posedge clk) begin
    if (!rst_n) begin
      expected_byte_idx <= 0;
      mismatch_count    <= 0;
      rgb_count         <= 0;
      ctrl_ok_count     <= 0;
      rgb_ok_count      <= 0;
    end else if (rgb_valid) begin
      rgb_count <= rgb_count + 1;
      check_byte(rgb_data[7:0]);
      check_byte(rgb_data[15:8]);
      check_byte(rgb_data[23:16]);
    end
  end

  initial begin
    $dumpfile("chpi_long_decoder_rgb24_line_tb.vcd");
    $dumpvars(0, chpi_long_decoder_rgb24_line_tb);

    for (i = 0; i < USEFUL_BITS; i = i + 1) useful_bits[i] = 1'b0;
    for (i = 0; i < ENCODED_BITS; i = i + 1) encoded_bits[i] = 1'b0;

    for (i = 0; i < LINE_BYTES; i = i + 1) begin
      value = line_byte(i);
      for (j = 0; j < 8; j = j + 1) begin
        useful_bits[i*8 + j] = value[j];
      end
    end

    enc_ptr = 0;
    for (blk = 0; blk < BLOCKS; blk = blk + 1) begin
      for (i = 0; i < 64; i = i + 1) used_label[i] = 1'b0;

      for (gi = 0; gi < 59; gi = gi + 1) begin
        group = 7'd0;
        for (bi = 0; bi < 7; bi = bi + 1) begin
          group[bi] = useful_bits[blk*413 + gi*7 + bi];
        end
        if ((group != 7'b0000000) && (group != 7'b1111111)) begin
          used_label[group[6:1]] = 1'b1;
        end
      end

      label_int = 1;
      while ((label_int < 63) && used_label[label_int]) label_int = label_int + 1;
      label = label_int[5:0];
      header_group = {1'b1, label};
      append_group(header_group);

      for (gi = 0; gi < 59; gi = gi + 1) begin
        group = 7'd0;
        for (bi = 0; bi < 7; bi = bi + 1) begin
          group[bi] = useful_bits[blk*413 + gi*7 + bi];
        end

        if (group == 7'b0000000) enc_group = {label, 1'b0};
        else if (group == 7'b1111111) enc_group = {label, 1'b1};
        else enc_group = group;
        append_group(enc_group);
      end
    end

    $display("One-line test: CTRL_L=%0d bytes, RGB=%0d bytes, total=%0d bytes",
             CTRL_BYTES, RGB_BYTES, LINE_BYTES);
    $display("Line bits=%0d, CHPI blocks=%0d, encoded bits=%0d, raw 20b clocks=%0d",
             LINE_BITS, BLOCKS, ENCODED_BITS, RAW_WORDS);
    $display("Decoder can emit %0d RGB24 words = %0d bytes; padding bytes checked as zero",
             OUT_RGB_WORDS, OUT_BYTES);

    rst_n = 1'b0;
    valid_i = 1'b0;
    chpi_in = 20'd0;
    repeat (5) @(posedge clk);
    rst_n = 1'b1;

    for (wi = 0; wi < RAW_WORDS; wi = wi + 1) begin
      drive_word = 20'd0;
      for (bi = 0; bi < 20; bi = bi + 1) begin
        drive_word[bi] = encoded_bits[wi*20 + bi];
      end
      @(negedge clk);
      valid_i = 1'b1;
      chpi_in = drive_word;
    end

    @(negedge clk);
    valid_i = 1'b0;
    chpi_in = 20'd0;

    repeat (120) @(posedge clk);

    if ((mismatch_count == 0) &&
        (ctrl_ok_count == CTRL_BYTES) &&
        (rgb_ok_count == RGB_BYTES) &&
        (expected_byte_idx >= LINE_BYTES)) begin
      $display("PASS: complete line matched: %0d CTRL_L bytes + %0d RGB bytes",
               ctrl_ok_count, rgb_ok_count);
      $display("Output RGB24 words=%0d, checked bytes=%0d", rgb_count, expected_byte_idx);
    end else begin
      $display("FAIL: mismatches=%0d ctrl_ok=%0d/%0d rgb_ok=%0d/%0d checked=%0d",
               mismatch_count, ctrl_ok_count, CTRL_BYTES,
               rgb_ok_count, RGB_BYTES, expected_byte_idx);
    end
    $finish;
  end
endmodule

chpi_long_decoder_rgb24_line_tb.vcd
$date
	Sun Jun 07 12:05:14 2026
$end
$version
	Icarus Verilog
$end
$timescale
	1ps
$end
$scope module chpi_long_decoder_rgb24_line_tb $end
$var wire 1 ! useful20_valid $end
$var wire 20 " useful20_data [19:0] $end
$var wire 1 # rgb_valid $end
$var wire 24 $ rgb_data [23:0] $end
$var parameter 32 % BLOCKS $end
$var parameter 32 & CTRL_BYTES $end
$var parameter 32 ' ENCODED_BITS $end
$var parameter 32 ( LINE_BITS $end
$var parameter 32 ) LINE_BYTES $end
$var parameter 32 * OUT_BYTES $end
$var parameter 32 + OUT_RGB_WORDS $end
$var parameter 32 , RAW_WORDS $end
$var parameter 32 - RGB_BYTES $end
$var parameter 32 . USEFUL_BITS $end
$var reg 20 / chpi_in [19:0] $end
$var reg 1 0 clk $end
$var reg 20 1 drive_word [19:0] $end
$var reg 7 2 enc_group [6:0] $end
$var reg 7 3 group [6:0] $end
$var reg 7 4 header_group [6:0] $end
$var reg 6 5 label [5:0] $end
$var reg 1 6 rst_n $end
$var reg 1 7 valid_i $end
$var reg 8 8 value [7:0] $end
$var integer 32 9 bi [31:0] $end
$var integer 32 : blk [31:0] $end
$var integer 32 ; ctrl_ok_count [31:0] $end
$var integer 32 < enc_ptr [31:0] $end
$var integer 32 = expected_byte_idx [31:0] $end
$var integer 32 > gi [31:0] $end
$var integer 32 ? i [31:0] $end
$var integer 32 @ j [31:0] $end
$var integer 32 A label_int [31:0] $end
$var integer 32 B mismatch_count [31:0] $end
$var integer 32 C rgb_count [31:0] $end
$var integer 32 D rgb_ok_count [31:0] $end
$var integer 32 E wi [31:0] $end
$scope function line_byte $end
$var integer 32 F idx [31:0] $end
$upscope $end
$scope module dut $end
$var wire 20 G chpi_in [19:0] $end
$var wire 1 0 clk $end
$var wire 1 6 rst_n $end
$var wire 1 7 valid_i $end
$var wire 1 ! useful20_valid $end
$var wire 20 H useful20_data [19:0] $end
$var wire 1 # rgb_valid $end
$var wire 24 I rgb_data [23:0] $end
$scope module u_dec $end
$var wire 20 J chpi_in [19:0] $end
$var wire 1 0 clk $end
$var wire 1 6 rst_n $end
$var wire 1 7 valid_i $end
$var reg 9 K bit_cnt_420 [8:0] $end
$var reg 9 L bit_cnt_420_next [8:0] $end
$var reg 7 M group_in [6:0] $end
$var reg 7 N group_out [6:0] $end
$var reg 6 O label_reg [5:0] $end
$var reg 6 P raw_cnt [5:0] $end
$var reg 6 Q raw_cnt_next [5:0] $end
$var reg 26 R raw_fifo [25:0] $end
$var reg 26 S raw_fifo_next [25:0] $end
$var reg 1 T replace_en $end
$var reg 6 U rgb_cnt [5:0] $end
$var reg 6 V rgb_cnt_next [5:0] $end
$var reg 24 W rgb_data [23:0] $end
$var reg 1 X rgb_emit_done $end
$var reg 32 Y rgb_fifo [31:0] $end
$var reg 32 Z rgb_fifo_next [31:0] $end
$var reg 1 # rgb_valid $end
$var reg 20 [ useful20_data [19:0] $end
$var reg 1 ! useful20_valid $end
$var reg 6 \ useful_cnt [5:0] $end
$var reg 6 ] useful_cnt_next [5:0] $end
$var reg 1 ^ useful_emit_done $end
$var reg 26 _ useful_fifo [25:0] $end
$var reg 26 ` useful_fifo_next [25:0] $end
$var integer 32 a k [31:0] $end
$upscope $end
$upscope $end
$scope task append_group $end
$var reg 7 b g [6:0] $end
$var integer 32 c n [31:0] $end
$upscope $end
$scope task check_byte $end
$var reg 8 d exp [7:0] $end
$var reg 8 e got [7:0] $end
$upscope $end
$upscope $end
$enddefinitions $end
$comment Show the parameter values. $end
$dumpall
b1111010100111 .
b1111000000 -
b110001111 ,
b101000110 +
b1111010010 *
b1111000101 )
b1111000101000 (
b1111100101100 '
b101 &
b10011 %
$end
#0
$dumpvars
bx e
bx d
b111 c
b100 b
bx a
bx `
b0 _
x^
bx ]
b0 \
b0 [
bx Z
b0 Y
xX
b0 W
bx V
b0 U
0T
bx S
b0 R
bx Q
b0 P
b0 O
bx N
bx M
bx L
b0 K
b0 J
b0 I
b0 H
b0 G
b1111000100 F
bx E
bx D
bx C
bx B
b10 A
b1000 @
b1000000 ?
b111011 >
bx =
b1111100101100 <
bx ;
b10011 :
b111 9
b10111111 8
07
06
b10 5
b1000010 4
b0 3
b100 2
bx 1
00
b0 /
b0 $
0#
b0 "
0!
$end
#5000
b0 D
b0 ;
b0 C
b0 B
b0 =
10
#10000
00
#15000
10
#20000
00
#25000
10
#30000
00
#35000
10
#40000
00
#45000
b11 a
0^
0X
b0 L
b0 ]
b0 `
b0 V
b0 Z
b0 Q
b0 S
b10100 9
b11110110000011000110 1
b0 E
16
10
#50000
b10100 9
b1010101001010101011 1
b1 E
b11110110000011000110 /
b11110110000011000110 G
b11110110000011000110 J
17
00
#55000
b1110 K
b111 \
b1000001 _
b111 U
b1000001 Y
b110 P
b111101 R
b111 ]
b1000001 `
b111 V
b1000001 Z
b1000001 N
b1110 L
1T
b110 O
b1000001 M
b11 a
b110 Q
b111101 S
10
#60000
b10100 9
b11001000000000101101 1
b10 E
b1010101001010101011 /
b1010101001010101011 G
b1010101001010101011 J
00
#65000
b100011 K
b1000 \
b10100101 _
b100 U
b1010 Y
b101 P
b1010 R
1#
b10101010111111011000001 $
b10101010111111011000001 I
b10101010111111011000001 W
1!
b1010111111011000001 "
b1010111111011000001 H
b1010111111011000001 [
1X
1^
b100011 L
b1000 ]
b10100101 `
b100 V
b1010 Z
b1010010 N
b1010010 M
b11 a
b101 Q
b1010 S
10
#70000
b10100 9
b1100000010000 1
b11 E
b11001000000000101101 /
b11001000000000101101 G
b11001000000000101101 J
00
#75000
b111000 K
b1001 \
b100000000 _
b1 U
b1 Y
b100 P
b1100 R
b101101010101010 $
b101101010101010 I
b101101010101010 W
b1011010101010100101 "
b1011010101010100101 H
b1011010101010100101 [
1!
1#
b1 C
b111000 L
b1001 ]
b100000000 `
b1 V
b1 Z
b1000000 N
b1000000 M
b11 a
b100 Q
b1100 S
1^
1X
b11 =
b11 ;
b1010101 d
b10 F
b1010101 e
10
#80000
b10100 9
b110000001010000010 1
b100 E
b1100000010000 /
b1100000010000 G
b1100000010000 J
00
#85000
b1001101 K
b1010 \
b110000 _
b10110 U
b110000001000000001 Y
b11 P
b0 R
b100000000100000000 "
b100000000100000000 H
b100000000100000000 [
1!
0#
b10 C
b110000 `
b110000001000000001 Z
b1001101 L
b1010 ]
b10110 V
b110 N
b110 M
b11 a
b11 Q
b0 S
1^
0X
b1 D
b110 =
b101 ;
b0 d
b101 F
b0 e
10
#90000
b10100 9
b10000100000000111000 1
b101 E
b110000001010000010 /
b110000001010000010 G
b110000001010000010 J
00
#95000
b1100010 K
b1011 \
b11000000101 _
b10011 U
b1100000010100000100 Y
b10 P
b100000000110000 "
b100000000110000 H
b100000000110000 [
1#
b110000001000000001 $
b110000001000000001 I
b110000001000000001 W
1!
b1100010 L
1X
b1011 ]
b11000000101 `
b10011 V
b1100000010100000100 Z
b1100000 N
b1100000 M
b11 a
b10 Q
b0 S
1^
10
#100000
b10100 9
b1011000010100000100 1
b110 E
b10000100000000111000 /
b10000100000000111000 G
b10000100000000111000 J
00
#105000
b1110111 K
b1100 \
b10000000 _
b10000 U
b100000000111 Y
b1 P
b1 R
b1110000011000000101 "
b1110000011000000101 H
b1110000011000000101 [
b1100000010100000100 $
b1100000010100000100 I
b1100000010100000100 W
1!
1#
b11 C
b100 N
b100 M
b1110111 L
b1100 ]
b10000000 `
b10000 V
b100000000111 Z
b11 a
b1 Q
b1 S
1^
1X
b1001 =
b100 D
b11 d
b1000 F
b11 e
10
#110000
b10100 9
b110100001100000 1
b111 E
b1011000010100000100 /
b1011000010100000100 G
b1011000010100000100 J
00
#115000
b10001100 K
b1101 \
b101100001010 _
b1101 U
b101100001010 Y
b0 P
b0 R
b1001000010000000 "
b1001000010000000 H
b1001000010000000 [
b10010000100000000111 $
b10010000100000000111 I
b10010000100000000111 W
1!
1#
b100 C
b10001100 L
b1101 ]
b101100001010 `
b1101 V
b101100001010 Z
b101100 N
b101100 M
b11 a
b0 Q
b0 S
1^
1X
b1100 =
b111 D
b110 d
b1011 F
b110 e
10
#120000
b10100 9
b10000000011110000111 1
b1000 E
b110100001100000 /
b110100001100000 G
b110100001100000 J
00
#125000
b10011010 K
b111 \
b1010000 _
b11 U
b101 Y
b110 P
b1 R
b11000000101100001010 $
b11000000101100001010 I
b11000000101100001010 W
b11000000101100001010 "
b11000000101100001010 H
b11000000101100001010 [
1!
1#
b101 C
b10011010 L
b111 ]
b1010000 `
b11 V
b101 Z
b1010000 N
b1010000 M
b11 a
b110 Q
b1 S
1^
1X
b1111 =
b1010 D
b1001 d
b1110 F
b1001 e
10
#130000
b10100 9
b10001001000010001000 1
b1001 E
b10000000011110000111 /
b10000000011110000111 G
b10000000011110000111 J
00
#135000
b10101111 K
b1000 \
b1111 _
b0 U
b0 Y
b101 P
b10000 R
b11110000111000001101 $
b11110000111000001101 I
b11110000111000001101 W
b1110000011010000 "
b1110000011010000 H
b1110000011010000 [
1!
1#
b110 C
b10101111 L
b1000 ]
b1111 `
b0 V
b0 Z
b111 N
b111 M
b11 a
b101 Q
b10000 S
1^
1X
b10010 =
b1101 D
b1100 d
b10001 F
b1100 e
10
#140000
b10100 9
b10101000101000001001 1
b1010 E
b10001001000010001000 /
b10001001000010001000 G
b10001001000010001000 J
00
#145000
b11000100 K
b1001 \
b100100001 _
b10101 U
b100100001000100010000 Y
b100 P
b1000 R
b10001000000001111 "
b10001000000001111 H
b10001000000001111 [
1!
0#
b111 C
b11000100 L
b1001 ]
b100100001 `
b10101 V
b100100001000100010000 Z
b1001000 N
b1001000 M
b11 a
b100 Q
b1000 S
1^
0X
b10101 =
b10000 D
b1111 d
b10100 F
b1111 e
10
#150000
b10100 9
b1011100010110000 1
b1011 E
b10101000101000001001 /
b10101000101000001001 G
b10101000101000001001 J
00
#155000
b11011001 K
b1010 \
b100010100 _
b10010 U
b10001010000010011 Y
b11 P
b101 R
b10011000100100001 "
b10011000100100001 H
b10011000100100001 [
1#
b100100001000100010000 $
b100100001000100010000 I
b100100001000100010000 W
1!
b11011001 L
1X
b1010 ]
b100010100 `
b10010 V
b10001010000010011 Z
b100010 N
b100010 M
b11 a
b11 Q
b101 S
1^
10
#160000
b10100 9
b11010000110010001100 1
b1100 E
b1011100010110000 /
b1011100010110000 G
b1011100010110000 J
00
#165000
b11101110 K
b1011 \
b101110001 _
b1111 U
b1011100010110 Y
b10 P
b0 R
b1100001010100010100 "
b1100001010100010100 H
b1100001010100010100 [
b101010001010000010011 $
b101010001010000010011 I
b101010001010000010011 W
1!
1#
b1000 C
b11101110 L
b1011 ]
b101110001 `
b1111 V
b1011100010110 Z
b10111 N
b10111 M
b11 a
b10 Q
b0 S
1^
1X
b11000 =
b10011 D
b10010 d
b10111 F
b10010 e
10
#170000
b10100 9
b10001110000011011000 1
b1101 E
b11010000110010001100 /
b11010000110010001100 G
b11010000110010001100 J
00
#175000
b100000011 K
b1100 \
b101000011001 _
b1100 U
b101000011001 Y
b1 P
b1 R
b11000000101110001 "
b11000000101110001 H
b11000000101110001 [
b110000001011100010110 $
b110000001011100010110 I
b110000001011100010110 W
1!
1#
b1001 C
b100000011 L
b1100 ]
b101000011001 `
b1100 V
b101000011001 Z
b1010000 N
b1010000 M
b11 a
b1 Q
b1 S
1^
1X
b11011 =
b10110 D
b10101 d
b11010 F
b10101 e
10
#180000
b10100 9
b11111000111100001110 1
b1110 E
b10001110000011011000 /
b10001110000011011000 G
b10001110000011011000 J
00
#185000
b100011000 K
b1101 \
b1000111000001 _
b1001 U
b100011100 Y
b0 P
b0 R
b10110001101000011001 "
b10110001101000011001 H
b10110001101000011001 [
b110110001101000011001 $
b110110001101000011001 I
b110110001101000011001 W
1!
1#
b1010 C
b100011000 L
b1101 ]
b1000111000001 `
b1001 V
b100011100 Z
b1000111 N
b1000111 M
b11 a
b0 Q
b0 S
1^
1X
b11110 =
b11001 D
b11000 d
b11101 F
b11000 e
10
#190000
b10100 9
b10000100100011000 1
b1111 E
b11111000111100001110 /
b11111000111100001110 G
b11111000111100001110 J
00
#195000
b100100110 K
b111 \
b11110 _
b10111 U
b111100001110100011100 Y
b110 P
b111110 R
b11101000111000001 "
b11101000111000001 H
b11101000111000001 [
1!
0#
b1011 C
b100100110 L
b111 ]
b11110 `
b10111 V
b111100001110100011100 Z
b11110 N
b11110 M
b11 a
b110 Q
b111110 S
1^
0X
b100001 =
b11100 D
b11011 d
b100000 F
b11011 e
10
#200000
b10100 9
b100001000110010001 1
b10000 E
b10000100100011000 /
b10000100100011000 G
b10000100100011000 J
00
#205000
b100111011 K
b1000 \
b10010 _
b10100 U
b10010000000011111 Y
b101 P
b10 R
b1111100011110 "
b1111100011110 H
b1111100011110 [
1#
b111100001110100011100 $
b111100001110100011100 I
b111100001110100011100 W
1!
b100111011 L
1X
b1000 ]
b10010 `
b10100 V
b10010000000011111 Z
b1001 N
b1001 M
b11 a
b101 Q
b10 S
1^
10
#210000
b10100 9
b10010011000100101001 1
b10001 E
b100001000110010001 /
b100001000110010001 G
b100001000110010001 J
00
#215000
b101010000 K
b1001 \
b100011 _
b10001 U
b10001100100010 Y
b100 P
b100010001000010010 "
b100010001000010010 H
b100010001000010010 [
b1000010010000000011111 $
b1000010010000000011111 I
b1000010010000000011111 W
1!
1#
b1100 C
b101010000 L
b1001 ]
b100011 `
b10001 V
b10001100100010 Z
b1000 N
b1000 M
b11 a
b100 Q
b10 S
1^
1X
b100100 =
b11111 D
b11110 d
b100011 F
b11110 e
10
#220000
b10100 9
b1001001010000010011 1
b10010 E
b10010011000100101001 /
b10010011000100101001 G
b10010011000100101001 J
00
#225000
b101100101 K
b1010 \
b1001100010 _
b1110 U
b10011000100101 Y
b11 P
b100 R
b1010010010000100011 "
b1010010010000100011 H
b1010010010000100011 [
b1001000010001100100010 $
b1001000010001100100010 I
b1001000010001100100010 W
1!
1#
b1101 C
b101100101 L
b1010 ]
b1001100010 `
b1110 V
b10011000100101 Z
b1001100 N
b1001100 M
b11 a
b11 Q
b100 S
1^
1X
b100111 =
b100010 D
b100001 d
b100110 F
b100001 e
10
#230000
b10100 9
b10101100101010001 1
b10011 E
b1001001010000010011 /
b1001001010000010011 G
b1001001010000010011 J
00
#235000
b101111010 K
b1011 \
b100101000 _
b1011 U
b100101000 Y
b10 P
b1 R
b100111001001100010 "
b100111001001100010 H
b100111001001100010 [
b1001110010011000100101 $
b1001110010011000100101 I
b1001110010011000100101 W
1!
1#
b1110 C
b101111010 L
b1011 ]
b100101000 `
b1011 V
b100101000 Z
b10010 N
b10010 M
b11 a
b10 Q
b1 S
1^
1X
b101010 =
b100101 D
b100100 d
b101001 F
b100100 e
10
#240000
b10100 9
b1110001011010010110 1
b10100 E
b10101100101010001 /
b10101100101010001 G
b10101100101010001 J
00
#245000
b110001111 K
b1100 \
b1010110010 _
b1000 U
b101011 Y
b1 P
b0 R
b10100010100100101000 "
b10100010100100101000 H
b10100010100100101000 [
b1010100010100100101000 $
b1010100010100100101000 I
b1010100010100100101000 W
1!
1#
b1111 C
b110001111 L
b1100 ]
b1010110010 `
b1000 V
b101011 Z
b10101 N
b10101 M
b11 a
b1 Q
b0 S
1^
1X
b101101 =
b101000 D
b100111 d
b101100 F
b100111 e
10
#250000
b10100 9
b1011110011000100 1
b10101 E
b1110001011010010110 /
b1110001011010010110 G
b1110001011010010110 J
00
#255000
b0 K
b1101 \
b111000101101 _
b101 U
b1110 Y
b0 P
b1011010010110000101011 $
b1011010010110000101011 I
b1011010010110000101011 W
b101100001010110010 "
b101100001010110010 H
b101100001010110010 [
1!
1#
b10000 C
b0 L
b1101 ]
b111000101101 `
b101 V
b1110 Z
b111000 N
b111000 M
b11 a
b0 Q
b0 S
1^
1X
b110000 =
b101011 D
b101010 d
b101111 F
b101010 e
10
#260000
b10100 9
b11001000110001001100 1
b10110 E
b1011110011000100 /
b1011110011000100 G
b1011110011000100 J
00
#265000
b1110 K
b0 \
b0 _
b1100 U
b111100101110 Y
b110 P
b10 R
b11110010111000101101 "
b11110010111000101101 H
b11110010111000101101 [
1!
0#
b10001 C
b0 ]
b0 `
b1100 V
b111100101110 Z
b1111001 N
b1110 L
b100 O
b1111001 M
b11 a
b110 Q
b10 S
1^
0X
b110011 =
b101110 D
b101101 d
b110010 F
b101101 e
10
#270000
b10100 9
b1001101000011001100 1
b10111 E
b11001000110001001100 /
b11001000110001001100 G
b11001000110001001100 J
00
#275000
b100011 K
b1 \
b1001 U
b110001 Y
b101 P
b11001 R
b110001001100000010 "
b110001001100000010 H
b110001001100000010 [
1#
b1100000010111100101110 $
b1100000010111100101110 I
b1100000010111100101110 W
1!
1X
b100011 L
b1 ]
b0 `
b1001 V
b110001 Z
b1100 N
b1100 M
b11 a
b101 Q
b11001 S
1^
10
#280000
b10100 9
b11011100110110001101 1
b11000 E
b1001101000011001100 /
b1001101000011001100 G
b1001101000011001100 J
00
#285000
b111000 K
b10 \
b11 _
b110 U
b110100 Y
b100 P
b100 R
b1000011001100110010 "
b1000011001100110010 H
b1000011001100110010 [
b1100110011001000110001 $
b1100110011001000110001 I
b1100110011001000110001 W
1!
1#
b10010 C
b111000 L
b10 ]
b11 `
b110 V
b110100 Z
b1101000 N
b1101000 M
b11 a
b100 Q
b100 S
1^
1X
b110110 =
b110001 D
b110000 d
b110101 F
b110000 e
10
#290000
b10100 9
b10001110010011100000 1
b11001 E
b11011100110110001101 /
b11011100110110001101 G
b11011100110110001101 J
00
#295000
b1001101 K
b11 \
b111 _
b11 U
b111 Y
b11 P
b110 R
b110110001101010011 "
b110110001101010011 H
b110110001101010011 [
b1101100011010100110100 $
b1101100011010100110100 I
b1101100011010100110100 W
1!
1#
b10011 C
b1001101 L
b11 ]
b111 `
b11 V
b111 Z
b1110011 N
b1110011 M
b11 a
b11 Q
b110 S
1^
1X
b111001 =
b110100 D
b110011 d
b111000 F
b110011 e
10
#300000
b10100 9
b11110000111011001110 1
b11010 E
b10001110010011100000 /
b10001110010011100000 G
b10001110010011100000 J
00
