chpi_long_decoder_rgb24_area_lean.v
`timescale 1ns/1ps

module chpi_decode_20b_stream_top (
  input  wire        clk,
  input  wire        rst_n,
  input  wire        valid_i,
  input  wire [19:0] chpi_in,
  output wire        rgb_valid,
  output wire [23:0] rgb_data,
  output wire        useful20_valid,
  output wire [19:0] useful20_data
);
  chpi_420b413b_rgb24_stream_dec u_dec (
    .clk            (clk),
    .rst_n          (rst_n),
    .valid_i        (valid_i),
    .chpi_in        (chpi_in),
    .rgb_valid      (rgb_valid),
    .rgb_data       (rgb_data),
    .useful20_valid (useful20_valid),
    .useful20_data  (useful20_data)
  );
endmodule

module chpi_420b413b_rgb24_stream_dec (
  input  wire        clk,
  input  wire        rst_n,
  input  wire        valid_i,
  input  wire [19:0] chpi_in,
  output reg         rgb_valid,
  output reg  [23:0] rgb_data,
  output wire        useful20_valid,
  output wire [19:0] useful20_data
);
  // This module is synthesis-intended RTL for the RGB24 path.
  // CHPI[19:0] enters LSB first. Each 420b packet is 7b header + 413b data.
  // The first 7b group is {H, Label}; it updates state and is not RGB data.

  assign useful20_valid = 1'b0;
  assign useful20_data  = 20'd0;

  localparam [4:0] RAW_GROUP_BITS = 5'd7;
  localparam [4:0] CHPI_BUS_BITS  = 5'd20;
  localparam [4:0] RGB_WORD_BITS  = 5'd24;
  localparam [8:0] LAST_413_POS   = 9'd413;

  // Raw aligner state. The registered residue is 0..6 bits after every clock.
  // After appending one 20b word, the temporary count is at most 26 bits.
  reg [25:0] raw_shift;
  reg [4:0]  raw_bit_count;

  // Packet/header state.
  reg [8:0]  packet_bit_count;
  reg [5:0]  active_label;
  reg        restore_enable;

  // RGB24 packer state. The registered residue is kept below 24 bits.
  // During one clock, 23 old bits + one 7b group needs a 30b shifter.
  reg [29:0] rgb_shift;
  reg [4:0]  rgb_bit_count;

  // Append current CHPI word before the three explicit parser stages.
  reg [25:0] append_raw_shift;
  reg [4:0]  append_raw_count;

  // Parser stage 0.
  reg [25:0] st0_raw_shift;
  reg [4:0]  st0_raw_count;
  reg [8:0]  st0_packet_bit_count;
  reg [5:0]  st0_label;
  reg        st0_restore_enable;
  reg        st0_payload_valid;
  reg [6:0]  st0_payload_bits;

  // Parser stage 1.
  reg [25:0] st1_raw_shift;
  reg [4:0]  st1_raw_count;
  reg [8:0]  st1_packet_bit_count;
  reg [5:0]  st1_label;
  reg        st1_restore_enable;
  reg        st1_payload_valid;
  reg [6:0]  st1_payload_bits;

  // Parser stage 2.
  reg [25:0] st2_raw_shift;
  reg [4:0]  st2_raw_count;
  reg [8:0]  st2_packet_bit_count;
  reg [5:0]  st2_label;
  reg        st2_restore_enable;
  reg        st2_payload_valid;
  reg [6:0]  st2_payload_bits;

  // RGB packer combinational result.
  reg [29:0] pack_shift;
  reg [4:0]  pack_count;
  reg        pack_emit_valid;
  reg [23:0] pack_emit_data;

  function [8:0] packet_count_after_group;
    input [8:0] count_now;
    begin
      if (count_now == LAST_413_POS) begin
        packet_count_after_group = 9'd0;
      end else begin
        packet_count_after_group = count_now + 9'd7;
      end
    end
  endfunction

  function [6:0] restore_payload_group;
    input [6:0] group_bits;
    input [5:0] label_bits;
    input       label_is_active;
    begin
      if (label_is_active && (group_bits[6:1] == label_bits)) begin
        if (group_bits[0]) begin
          restore_payload_group = 7'b1111111;
        end else begin
          restore_payload_group = 7'b0000000;
        end
      end else begin
        restore_payload_group = group_bits;
      end
    end
  endfunction

  always @* begin
    append_raw_shift = raw_shift;
    append_raw_count = raw_bit_count;

    if (valid_i) begin
      append_raw_shift = raw_shift | ({{6{1'b0}}, chpi_in} << raw_bit_count);
      append_raw_count = raw_bit_count + CHPI_BUS_BITS;
    end else begin
      append_raw_shift = raw_shift;
      append_raw_count = raw_bit_count;
    end
  end

  // Stage 0: first possible 7b group in this clock.
  always @* begin
    st0_raw_shift        = append_raw_shift;
    st0_raw_count        = append_raw_count;
    st0_packet_bit_count = packet_bit_count;
    st0_label            = active_label;
    st0_restore_enable   = restore_enable;
    st0_payload_valid    = 1'b0;
    st0_payload_bits     = 7'd0;

    if (append_raw_count >= RAW_GROUP_BITS) begin
      if (packet_bit_count == 9'd0) begin
        st0_label          = append_raw_shift[5:0];
        st0_restore_enable = (append_raw_shift[5:0] != {6{~append_raw_shift[6]}});
        st0_payload_valid  = 1'b0;
        st0_payload_bits   = 7'd0;
      end else begin
        st0_label          = active_label;
        st0_restore_enable = restore_enable;
        st0_payload_valid  = 1'b1;
        st0_payload_bits   = restore_payload_group(append_raw_shift[6:0],
                                                   active_label,
                                                   restore_enable);
      end

      st0_raw_shift        = append_raw_shift >> RAW_GROUP_BITS;
      st0_raw_count        = append_raw_count - RAW_GROUP_BITS;
      st0_packet_bit_count = packet_count_after_group(packet_bit_count);
    end else begin
      st0_raw_shift        = append_raw_shift;
      st0_raw_count        = append_raw_count;
      st0_packet_bit_count = packet_bit_count;
      st0_label            = active_label;
      st0_restore_enable   = restore_enable;
      st0_payload_valid    = 1'b0;
      st0_payload_bits     = 7'd0;
    end
  end

  // Stage 1: second possible 7b group in this clock.
  always @* begin
    st1_raw_shift        = st0_raw_shift;
    st1_raw_count        = st0_raw_count;
    st1_packet_bit_count = st0_packet_bit_count;
    st1_label            = st0_label;
    st1_restore_enable   = st0_restore_enable;
    st1_payload_valid    = 1'b0;
    st1_payload_bits     = 7'd0;

    if (st0_raw_count >= RAW_GROUP_BITS) begin
      if (st0_packet_bit_count == 9'd0) begin
        st1_label          = st0_raw_shift[5:0];
        st1_restore_enable = (st0_raw_shift[5:0] != {6{~st0_raw_shift[6]}});
        st1_payload_valid  = 1'b0;
        st1_payload_bits   = 7'd0;
      end else begin
        st1_label          = st0_label;
        st1_restore_enable = st0_restore_enable;
        st1_payload_valid  = 1'b1;
        st1_payload_bits   = restore_payload_group(st0_raw_shift[6:0],
                                                   st0_label,
                                                   st0_restore_enable);
      end

      st1_raw_shift        = st0_raw_shift >> RAW_GROUP_BITS;
      st1_raw_count        = st0_raw_count - RAW_GROUP_BITS;
      st1_packet_bit_count = packet_count_after_group(st0_packet_bit_count);
    end else begin
      st1_raw_shift        = st0_raw_shift;
      st1_raw_count        = st0_raw_count;
      st1_packet_bit_count = st0_packet_bit_count;
      st1_label            = st0_label;
      st1_restore_enable   = st0_restore_enable;
      st1_payload_valid    = 1'b0;
      st1_payload_bits     = 7'd0;
    end
  end

  // Stage 2: third possible 7b group in this clock.
  always @* begin
    st2_raw_shift        = st1_raw_shift;
    st2_raw_count        = st1_raw_count;
    st2_packet_bit_count = st1_packet_bit_count;
    st2_label            = st1_label;
    st2_restore_enable   = st1_restore_enable;
    st2_payload_valid    = 1'b0;
    st2_payload_bits     = 7'd0;

    if (st1_raw_count >= RAW_GROUP_BITS) begin
      if (st1_packet_bit_count == 9'd0) begin
        st2_label          = st1_raw_shift[5:0];
        st2_restore_enable = (st1_raw_shift[5:0] != {6{~st1_raw_shift[6]}});
        st2_payload_valid  = 1'b0;
        st2_payload_bits   = 7'd0;
      end else begin
        st2_label          = st1_label;
        st2_restore_enable = st1_restore_enable;
        st2_payload_valid  = 1'b1;
        st2_payload_bits   = restore_payload_group(st1_raw_shift[6:0],
                                                   st1_label,
                                                   st1_restore_enable);
      end

      st2_raw_shift        = st1_raw_shift >> RAW_GROUP_BITS;
      st2_raw_count        = st1_raw_count - RAW_GROUP_BITS;
      st2_packet_bit_count = packet_count_after_group(st1_packet_bit_count);
    end else begin
      st2_raw_shift        = st1_raw_shift;
      st2_raw_count        = st1_raw_count;
      st2_packet_bit_count = st1_packet_bit_count;
      st2_label            = st1_label;
      st2_restore_enable   = st1_restore_enable;
      st2_payload_valid    = 1'b0;
      st2_payload_bits     = 7'd0;
    end
  end

  // RGB24 packer. It appends stage0/1/2 payload groups in order and emits at
  // most one 24b RGB word per clock.
  always @* begin
    pack_shift      = rgb_shift;
    pack_count      = rgb_bit_count;
    pack_emit_valid = 1'b0;
    pack_emit_data  = 24'd0;

    if (st0_payload_valid) begin
      pack_shift = pack_shift | ({{23{1'b0}}, st0_payload_bits} << pack_count);
      pack_count = pack_count + RAW_GROUP_BITS;
      if (pack_count >= RGB_WORD_BITS) begin
        pack_emit_data  = pack_shift[23:0];
        pack_emit_valid = 1'b1;
        pack_shift      = pack_shift >> RGB_WORD_BITS;
        pack_count      = pack_count - RGB_WORD_BITS;
      end else begin
        pack_emit_data  = 24'd0;
        pack_emit_valid = 1'b0;
      end
    end else begin
      // No stage0 payload; keep defaults from the current RGB packer state.
    end

    if (st1_payload_valid) begin
      pack_shift = pack_shift | ({{23{1'b0}}, st1_payload_bits} << pack_count);
      pack_count = pack_count + RAW_GROUP_BITS;
      if (!pack_emit_valid && (pack_count >= RGB_WORD_BITS)) begin
        pack_emit_data  = pack_shift[23:0];
        pack_emit_valid = 1'b1;
        pack_shift      = pack_shift >> RGB_WORD_BITS;
        pack_count      = pack_count - RGB_WORD_BITS;
      end else begin
        // Either no RGB24 is ready yet, or this clock already emitted one.
      end
    end else begin
      // No stage1 payload; keep the result from prior packer steps.
    end

    if (st2_payload_valid) begin
      pack_shift = pack_shift | ({{23{1'b0}}, st2_payload_bits} << pack_count);
      pack_count = pack_count + RAW_GROUP_BITS;
      if (!pack_emit_valid && (pack_count >= RGB_WORD_BITS)) begin
        pack_emit_data  = pack_shift[23:0];
        pack_emit_valid = 1'b1;
        pack_shift      = pack_shift >> RGB_WORD_BITS;
        pack_count      = pack_count - RGB_WORD_BITS;
      end else begin
        // Either no RGB24 is ready yet, or this clock already emitted one.
      end
    end else begin
      // No stage2 payload; keep the result from prior packer steps.
    end
  end

  always @(posedge clk or negedge rst_n) begin
    if (!rst_n) begin
      raw_shift     <= 26'd0;
      raw_bit_count <= 5'd0;
    end else begin
      raw_shift     <= st2_raw_shift;
      raw_bit_count <= st2_raw_count;
    end
  end

  always @(posedge clk or negedge rst_n) begin
    if (!rst_n) begin
      packet_bit_count <= 9'd0;
    end else begin
      packet_bit_count <= st2_packet_bit_count;
    end
  end

  always @(posedge clk or negedge rst_n) begin
    if (!rst_n) begin
      active_label   <= 6'd0;
      restore_enable <= 1'b0;
    end else begin
      active_label   <= st2_label;
      restore_enable <= st2_restore_enable;
    end
  end

  always @(posedge clk or negedge rst_n) begin
    if (!rst_n) begin
      rgb_shift     <= 30'd0;
      rgb_bit_count <= 5'd0;
    end else begin
      rgb_shift     <= pack_shift;
      rgb_bit_count <= pack_count;
    end
  end

  always @(posedge clk or negedge rst_n) begin
    if (!rst_n) begin
      rgb_valid <= 1'b0;
      rgb_data  <= 24'd0;
    end else begin
      rgb_valid <= pack_emit_valid;
      if (pack_emit_valid) begin
        rgb_data <= pack_emit_data;
      end else begin
        rgb_data <= 24'd0;
      end
    end
  end
endmodule

chpi_long_decoder_rgb24_line_tb.v
`timescale 1ns/1ps

module chpi_long_decoder_rgb24_line_tb;
  localparam integer CTRL_BYTES   = 5;
  localparam integer RGB_BYTES    = 960;
  localparam integer LINE_BYTES   = CTRL_BYTES + RGB_BYTES;
  localparam integer LINE_BITS    = LINE_BYTES * 8;
  localparam integer BLOCKS       = (LINE_BITS + 412) / 413;
  localparam integer USEFUL_BITS  = BLOCKS * 413;
  localparam integer ENCODED_BITS = BLOCKS * 420;
  localparam integer RAW_WORDS    = ENCODED_BITS / 20;
  localparam integer OUT_RGB_WORDS = USEFUL_BITS / 24;
  localparam integer OUT_BYTES    = OUT_RGB_WORDS * 3;

  reg clk;
  reg rst_n;
  reg valid_i;
  reg [19:0] chpi_in;
  wire rgb_valid;
  wire [23:0] rgb_data;
  wire useful20_valid;
  wire [19:0] useful20_data;

  reg useful_bits [0:USEFUL_BITS-1];
  reg encoded_bits [0:ENCODED_BITS-1];
  reg used_label [0:63];

  integer i, j, blk, gi, bi, wi;
  integer enc_ptr;
  integer expected_byte_idx;
  integer mismatch_count;
  integer rgb_count;
  integer ctrl_ok_count;
  integer rgb_ok_count;
  reg [6:0] group;
  reg [6:0] enc_group;
  reg [6:0] header_group;
  reg [5:0] label;
  integer label_int;
  reg [7:0] value;
  reg [19:0] drive_word;

  chpi_decode_20b_stream_top dut (
    .clk            (clk),
    .rst_n          (rst_n),
    .valid_i        (valid_i),
    .chpi_in        (chpi_in),
    .rgb_valid      (rgb_valid),
    .rgb_data       (rgb_data),
    .useful20_valid (useful20_valid),
    .useful20_data  (useful20_data)
  );

  initial begin
    clk = 1'b0;
    forever #5 clk = ~clk; // 100 MHz
  end

  function [7:0] line_byte;
    input integer idx;
    begin
      case (idx)
        0: line_byte = 8'hc1;
        1: line_byte = 8'h7e;
        2: line_byte = 8'h55;
        3: line_byte = 8'haa;
        4: line_byte = 8'h5a;
        default: line_byte = (idx - CTRL_BYTES) & 8'hff;
      endcase
    end
  endfunction

  task append_group;
    input [6:0] g;
    integer n;
    begin
      for (n = 0; n < 7; n = n + 1) begin
        encoded_bits[enc_ptr] = g[n];
        enc_ptr = enc_ptr + 1;
      end
    end
  endtask

  task check_byte;
    input [7:0] got;
    reg [7:0] exp;
    begin
      if (expected_byte_idx < LINE_BYTES) begin
        exp = line_byte(expected_byte_idx);
        if (got !== exp) begin
          $display("ERROR line_byte[%0d] got=%02x exp=%02x time=%0t",
                   expected_byte_idx, got, exp, $time);
          mismatch_count = mismatch_count + 1;
        end else if (expected_byte_idx < CTRL_BYTES) begin
          ctrl_ok_count = ctrl_ok_count + 1;
          $display("CTRL PASS byte[%0d] = %02x time=%0t",
                   expected_byte_idx, got, $time);
        end else begin
          rgb_ok_count = rgb_ok_count + 1;
          if ((expected_byte_idx == CTRL_BYTES) ||
              (expected_byte_idx == CTRL_BYTES + RGB_BYTES - 1)) begin
            $display("RGB PASS byte[%0d] = %02x time=%0t",
                     expected_byte_idx - CTRL_BYTES, got, $time);
          end
        end
      end else if (got !== 8'h00) begin
        $display("ERROR padding_byte[%0d] got=%02x exp=00 time=%0t",
                 expected_byte_idx - LINE_BYTES, got, $time);
        mismatch_count = mismatch_count + 1;
      end
      expected_byte_idx = expected_byte_idx + 1;
    end
  endtask

  always @(posedge clk) begin
    if (!rst_n) begin
      expected_byte_idx <= 0;
      mismatch_count    <= 0;
      rgb_count         <= 0;
      ctrl_ok_count     <= 0;
      rgb_ok_count      <= 0;
    end else if (rgb_valid) begin
      rgb_count <= rgb_count + 1;
      check_byte(rgb_data[7:0]);
      check_byte(rgb_data[15:8]);
      check_byte(rgb_data[23:16]);
    end
  end

  initial begin
    $dumpfile("chpi_long_decoder_rgb24_line_tb.vcd");
    $dumpvars(0, chpi_long_decoder_rgb24_line_tb);

    for (i = 0; i < USEFUL_BITS; i = i + 1) useful_bits[i] = 1'b0;
    for (i = 0; i < ENCODED_BITS; i = i + 1) encoded_bits[i] = 1'b0;

    for (i = 0; i < LINE_BYTES; i = i + 1) begin
      value = line_byte(i);
      for (j = 0; j < 8; j = j + 1) begin
        useful_bits[i*8 + j] = value[j];
      end
    end

    enc_ptr = 0;
    for (blk = 0; blk < BLOCKS; blk = blk + 1) begin
      for (i = 0; i < 64; i = i + 1) used_label[i] = 1'b0;

      for (gi = 0; gi < 59; gi = gi + 1) begin
        group = 7'd0;
        for (bi = 0; bi < 7; bi = bi + 1) begin
          group[bi] = useful_bits[blk*413 + gi*7 + bi];
        end
        if ((group != 7'b0000000) && (group != 7'b1111111)) begin
          used_label[group[6:1]] = 1'b1;
        end
      end

      label_int = 1;
      while ((label_int < 63) && used_label[label_int]) label_int = label_int + 1;
      label = label_int[5:0];
      header_group = {1'b1, label};
      append_group(header_group);

      for (gi = 0; gi < 59; gi = gi + 1) begin
        group = 7'd0;
        for (bi = 0; bi < 7; bi = bi + 1) begin
          group[bi] = useful_bits[blk*413 + gi*7 + bi];
        end

        if (group == 7'b0000000) enc_group = {label, 1'b0};
        else if (group == 7'b1111111) enc_group = {label, 1'b1};
        else enc_group = group;
        append_group(enc_group);
      end
    end

    $display("One-line test: CTRL_L=%0d bytes, RGB=%0d bytes, total=%0d bytes",
             CTRL_BYTES, RGB_BYTES, LINE_BYTES);
    $display("Line bits=%0d, CHPI blocks=%0d, encoded bits=%0d, raw 20b clocks=%0d",
             LINE_BITS, BLOCKS, ENCODED_BITS, RAW_WORDS);
    $display("Decoder can emit %0d RGB24 words = %0d bytes; padding bytes checked as zero",
             OUT_RGB_WORDS, OUT_BYTES);

    rst_n = 1'b0;
    valid_i = 1'b0;
    chpi_in = 20'd0;
    repeat (5) @(posedge clk);
    rst_n = 1'b1;

    for (wi = 0; wi < RAW_WORDS; wi = wi + 1) begin
      drive_word = 20'd0;
      for (bi = 0; bi < 20; bi = bi + 1) begin
        drive_word[bi] = encoded_bits[wi*20 + bi];
      end
      @(negedge clk);
      valid_i = 1'b1;
      chpi_in = drive_word;
    end

    @(negedge clk);
    valid_i = 1'b0;
    chpi_in = 20'd0;

    repeat (120) @(posedge clk);

    if ((mismatch_count == 0) &&
        (ctrl_ok_count == CTRL_BYTES) &&
        (rgb_ok_count == RGB_BYTES) &&
        (expected_byte_idx >= LINE_BYTES)) begin
      $display("PASS: complete line matched: %0d CTRL_L bytes + %0d RGB bytes",
               ctrl_ok_count, rgb_ok_count);
      $display("Output RGB24 words=%0d, checked bytes=%0d", rgb_count, expected_byte_idx);
    end else begin
      $display("FAIL: mismatches=%0d ctrl_ok=%0d/%0d rgb_ok=%0d/%0d checked=%0d",
               mismatch_count, ctrl_ok_count, CTRL_BYTES,
               rgb_ok_count, RGB_BYTES, expected_byte_idx);
    end
    $finish;
  end
endmodule

chpi_long_decoder_rgb24_line_tb.vcd
$date
	Sun Jun 07 23:38:08 2026
$end
$version
	Icarus Verilog
$end
$timescale
	1ps
$end
$scope module chpi_long_decoder_rgb24_line_tb $end
$var wire 20 ! useful20_data [19:0] $end
$var wire 1 " useful20_valid $end
$var wire 1 # rgb_valid $end
$var wire 24 $ rgb_data [23:0] $end
$var parameter 32 % BLOCKS $end
$var parameter 32 & CTRL_BYTES $end
$var parameter 32 ' ENCODED_BITS $end
$var parameter 32 ( LINE_BITS $end
$var parameter 32 ) LINE_BYTES $end
$var parameter 32 * OUT_BYTES $end
$var parameter 32 + OUT_RGB_WORDS $end
$var parameter 32 , RAW_WORDS $end
$var parameter 32 - RGB_BYTES $end
$var parameter 32 . USEFUL_BITS $end
$var reg 20 / chpi_in [19:0] $end
$var reg 1 0 clk $end
$var reg 20 1 drive_word [19:0] $end
$var reg 7 2 enc_group [6:0] $end
$var reg 7 3 group [6:0] $end
$var reg 7 4 header_group [6:0] $end
$var reg 6 5 label [5:0] $end
$var reg 1 6 rst_n $end
$var reg 1 7 valid_i $end
$var reg 8 8 value [7:0] $end
$var integer 32 9 bi [31:0] $end
$var integer 32 : blk [31:0] $end
$var integer 32 ; ctrl_ok_count [31:0] $end
$var integer 32 < enc_ptr [31:0] $end
$var integer 32 = expected_byte_idx [31:0] $end
$var integer 32 > gi [31:0] $end
$var integer 32 ? i [31:0] $end
$var integer 32 @ j [31:0] $end
$var integer 32 A label_int [31:0] $end
$var integer 32 B mismatch_count [31:0] $end
$var integer 32 C rgb_count [31:0] $end
$var integer 32 D rgb_ok_count [31:0] $end
$var integer 32 E wi [31:0] $end
$scope function line_byte $end
$var integer 32 F idx [31:0] $end
$upscope $end
$scope module dut $end
$var wire 20 G chpi_in [19:0] $end
$var wire 1 0 clk $end
$var wire 1 6 rst_n $end
$var wire 20 H useful20_data [19:0] $end
$var wire 1 " useful20_valid $end
$var wire 1 7 valid_i $end
$var wire 1 # rgb_valid $end
$var wire 24 I rgb_data [23:0] $end
$scope module u_dec $end
$var wire 20 J chpi_in [19:0] $end
$var wire 1 0 clk $end
$var wire 1 6 rst_n $end
$var wire 20 K useful20_data [19:0] $end
$var wire 1 " useful20_valid $end
$var wire 1 7 valid_i $end
$var parameter 5 L CHPI_BUS_BITS $end
$var parameter 9 M LAST_413_POS $end
$var parameter 5 N RAW_GROUP_BITS $end
$var parameter 5 O RGB_WORD_BITS $end
$var reg 6 P active_label [5:0] $end
$var reg 5 Q append_raw_count [4:0] $end
$var reg 26 R append_raw_shift [25:0] $end
$var reg 5 S pack_count [4:0] $end
$var reg 24 T pack_emit_data [23:0] $end
$var reg 1 U pack_emit_valid $end
$var reg 30 V pack_shift [29:0] $end
$var reg 9 W packet_bit_count [8:0] $end
$var reg 5 X raw_bit_count [4:0] $end
$var reg 26 Y raw_shift [25:0] $end
$var reg 1 Z restore_enable $end
$var reg 5 [ rgb_bit_count [4:0] $end
$var reg 24 \ rgb_data [23:0] $end
$var reg 30 ] rgb_shift [29:0] $end
$var reg 1 # rgb_valid $end
$var reg 6 ^ st0_label [5:0] $end
$var reg 9 _ st0_packet_bit_count [8:0] $end
$var reg 7 ` st0_payload_bits [6:0] $end
$var reg 1 a st0_payload_valid $end
$var reg 5 b st0_raw_count [4:0] $end
$var reg 26 c st0_raw_shift [25:0] $end
$var reg 1 d st0_restore_enable $end
$var reg 6 e st1_label [5:0] $end
$var reg 9 f st1_packet_bit_count [8:0] $end
$var reg 7 g st1_payload_bits [6:0] $end
$var reg 1 h st1_payload_valid $end
$var reg 5 i st1_raw_count [4:0] $end
$var reg 26 j st1_raw_shift [25:0] $end
$var reg 1 k st1_restore_enable $end
$var reg 6 l st2_label [5:0] $end
$var reg 9 m st2_packet_bit_count [8:0] $end
$var reg 7 n st2_payload_bits [6:0] $end
$var reg 1 o st2_payload_valid $end
$var reg 5 p st2_raw_count [4:0] $end
$var reg 26 q st2_raw_shift [25:0] $end
$var reg 1 r st2_restore_enable $end
$scope function packet_count_after_group $end
$var reg 9 s count_now [8:0] $end
$upscope $end
$scope function restore_payload_group $end
$var reg 7 t group_bits [6:0] $end
$var reg 6 u label_bits [5:0] $end
$var reg 1 v label_is_active $end
$upscope $end
$upscope $end
$upscope $end
$scope task append_group $end
$var reg 7 w g [6:0] $end
$var integer 32 x n [31:0] $end
$upscope $end
$scope task check_byte $end
$var reg 8 y exp [7:0] $end
$var reg 8 z got [7:0] $end
$upscope $end
$upscope $end
$enddefinitions $end
$comment Show the parameter values. $end
$dumpall
b11000 O
b111 N
b110011101 M
b10100 L
b1111010100111 .
b1111000000 -
b110001111 ,
b101000110 +
b1111010010 *
b1111000101 )
b1111000101000 (
b1111100101100 '
b101 &
b10011 %
$end
#0
$dumpvars
bx z
bx y
b111 x
b100 w
xv
bx u
bx t
bx s
0r
b0 q
b0 p
0o
b0 n
b0 m
b0 l
0k
b0 j
b0 i
0h
b0 g
b0 f
b0 e
0d
b0 c
b0 b
0a
b0 `
b0 _
b0 ^
b0 ]
b0 \
b0 [
0Z
b0 Y
b0 X
b0 W
b0 V
0U
b0 T
b0 S
b0 R
b0 Q
b0 P
b0 K
b0 J
b0 I
b0 H
b0 G
b1111000100 F
bx E
bx D
bx C
bx B
b10 A
b1000 @
b1000000 ?
b111011 >
bx =
b1111100101100 <
bx ;
b10011 :
b111 9
b10111111 8
07
06
b10 5
b1000010 4
b0 3
b100 2
bx 1
00
b0 /
b0 $
0#
0"
b0 !
$end
#5000
b0 D
b0 ;
b0 C
b0 B
b0 =
10
#10000
00
#15000
10
#20000
00
#25000
10
#30000
00
#35000
10
#40000
00
#45000
b10100 9
b11110110000011000110 1
b0 E
16
10
#50000
b111 S
b1000001 V
1r
b110 l
b1110 m
b110 p
b111101 q
b1000001 g
b1000001 t
b110 u
1v
1h
1k
b110 e
b1110 f
b110 i
b111101 j
b111 _
b111 s
1d
b110 ^
b1101 b
b1111011000001 c
b10100 Q
b11110110000011000110 R
b10100 9
b1010101001010101011 1
b1 E
b11110110000011000110 /
b11110110000011000110 G
b11110110000011000110 J
17
00
#55000
1U
b110001101111011000001 T
b1100000 n
1o
b101 p
b11110 q
b100011 m
b1100011 g
1h
b11100 f
b1100 i
b111101100000 j
b11010 Q
b11110110000011000110111101 R
b11100 s
b111101 `
b1100000 t
1a
b10101 _
b10011 b
b1111011000001100011 c
b100 S
b1100 V
b110 X
b111101 Y
b1110 W
1Z
b110 P
b111 [
b1000001 ]
10
#60000
b1010010 n
1o
b100011 m
b101 p
b1010 q
b10101010111111011000001 T
1U
b100 S
b1010 V
b1010101 g
1h
b11100 f
b1100 i
b10101010010 j
b11100 s
b1010010 t
b1111101 `
1a
b10101 _
b10011 b
b101010100101010101 c
b11010 Q
b1010101001010101011111101 R
b10100 9
b11001000000000101101 1
b10 E
b1010101001010101011 /
b1010101001010101011 G
b1010101001010101011 J
00
#65000
b101001 n
1o
b111000 m
b100 p
b101 q
b101010 g
1h
b110001 f
b1011 i
b1010101001 j
b1 S
b0 V
b101001010101011010101010 T
1U
b110001 s
b101001 t
b1101010 `
1a
b101010 _
b10010 b
b10101010010101010 c
b11001 Q
b101010100101010101101010 R
b10101010111111011000001 $
b10101010111111011000001 I
b10101010111111011000001 \
1#
b100 [
b1010 ]
b100011 W
b101 X
b1010 Y
10
#70000
b1000000 n
1o
b111000 m
b100 p
b1100 q
b101101010101010 T
1U
b1 S
b1 V
b1011 g
1h
b110001 f
b1011 i
b11001000000 j
b110001 s
b1000000 t
b101010 `
1a
b101010 _
b10010 b
b110010000000001011 c
b11001 Q
b1100100000000010110101010 R
b10100 9
b1100000010000 1
b11 E
b11001000000000101101 /
b11001000000000101101 G
b11001000000000101101 J
00
#75000
b100000 n
1o
b1001101 m
b11 p
b110 q
b101 g
1h
b1000110 f
b1010 i
b1100100000 j
b11000 Q
b110010000000001011011100 R
b1000110 s
b100000 t
b1011100 `
1a
b111111 _
b10001 b
b11001000000000101 c
b10110 S
b100000000010110111001 V
b0 T
0U
b100 X
b1100 Y
b111000 W
b1 [
b1 ]
b101101010101010 $
b101101010101010 I
b101101010101010 \
b1 C
b11 =
b11 ;
b1010101 y
b10 F
b1010101 z
10
#80000
b0 q
b110 n
1o
b1001101 m
b11 p
b10110 S
b110000001000000001 V
b10 g
1h
b1000110 f
b1010 i
b110 j
b1000110 s
b110 t
b0 `
1a
b111111 _
b10001 b
b1100000010 c
b11000 Q
b11000000100001100 R
b10100 9
b110000001010000010 1
b100 E
b1100000010000 /
b1100000010000 G
b1100000010000 J
00
#85000
b11 n
1o
b1100010 m
b10 p
b0 q
b1 g
1h
b1011011 f
b1001 i
b11 j
b11000000100000 V
1U
b110000001000000001 T
b10011 S
b1011011 s
b11 t
1a
b1010100 _
b10000 b
b110000001 c
b10111 Q
b1100000010000000 R
b0 $
b0 I
b0 \
0#
b10110 [
b110000001000000001 ]
b1001101 W
b11 X
b0 Y
b10 C
b1 D
b110 =
b101 ;
b0 y
b101 F
b0 z
10
#90000
b1100000 n
1o
b1100010 m
b10 p
b0 q
b110000001000000001 T
1U
b10011 S
b1100000010100000100 V
b101000 g
1h
b1011011 f
b1001 i
b1100000 j
b1011011 s
b10000 `
b1100000 t
1a
b1010100 _
b10000 b
b11000000101000 c
b10111 Q
b110000001010000010000 R
b10100 9
b10000100000000111000 1
b101 E
b110000001010000010 /
b110000001010000010 G
b110000001010000010 J
00
#95000
b110000 n
1o
b1110111 m
b1 p
b0 q
b10100 g
1h
b1110000 f
b1000 i
b110000 j
b10110 Q
b11000000101000001000 R
b1110000 s
b110000 t
b1000 `
1a
b1101001 _
b1111 b
b1100000010100 c
b10000 S
b110000001010000 V
b10001100000010100000100 T
1U
b10 X
b1100010 W
b10011 [
b1100000010100000100 ]
b110000001000000001 $
b110000001000000001 I
b110000001000000001 \
1#
10
#100000
b100 n
1o
b1110111 m
b1 p
b1 q
b1100000010100000100 T
1U
b10000 S
b100000000111 V
b1 g
1h
b1110000 f
b1000 i
b10000100 j
b1110000 s
b100 t
b1100000 `
1a
b1101001 _
b1111 b
b100001000000001 c
b10110 Q
b1000010000000011100000 R
b10100 9
b1011000010100000100 1
b110 E
b10000100000000111000 /
b10000100000000111000 G
b10000100000000111000 J
00
#105000
b1000010 n
1o
b10001100 m
b0 p
b0 q
b0 g
1h
b10000101 f
b111 i
b1000010 j
b1101 S
b1000010000000 V
b11100010000100000000111 T
1U
b10000101 s
b1000010 t
b1110001 `
1a
b1111110 _
b1110 b
b10000100000000 c
b10101 Q
b100001000000001110001 R
b1100000010100000100 $
b1100000010100000100 I
b1100000010100000100 \
b10000 [
b100000000111 ]
b1110111 W
b1 X
b1 Y
b11 C
b1001 =
b100 D
b11 y
b1000 F
b11 z
10
#110000
b101100 n
1o
b10001100 m
b0 p
b0 q
b10010000100000000111 T
1U
b1101 S
b101100001010 V
b10100 g
1h
b10000101 f
b111 i
b101100 j
b10000101 s
b101100 t
b1001 `
1a
b1111110 _
b1110 b
b1011000010100 c
b10101 Q
b10110000101000001001 R
b10100 9
b110100001100000 1
b111 E
b1011000010100000100 /
b1011000010100000100 G
b1011000010100000100 J
00
#115000
b0 n
0o
b10011010 m
b110 p
b10110 q
b1010 g
1h
b10011010 f
b110 i
b10110 j
b10100 Q
b1011000010100000100 R
b10010011 s
b1010 t
b100 `
1a
b10010011 _
b1101 b
b101100001010 c
b11 S
b0 V
b101000001000101100001010 T
1U
b0 X
b0 Y
b10001100 W
b1101 [
b101100001010 ]
b10010000100000000111 $
b10010000100000000111 I
b10010000100000000111 \
b100 C
b1100 =
b111 D
b110 y
b1011 F
b110 z
10
#120000
b1 q
b11000000101100001010 T
1U
b11 S
b101 V
b1010000 g
1h
b10011010 f
b110 i
b1 j
b10010011 s
b1010000 t
b1100000 `
1a
b10010011 _
b1101 b
b11010000 c
b10100 Q
b110100001100000 R
b10100 9
b10000000011110000111 1
b1000 E
b110100001100000 /
b110100001100000 G
b110100001100000 J
00
